{
  "hash": "33ef22863f8e8a8325bc405c8322e46f",
  "result": {
    "engine": "knitr",
    "markdown": "---\nformat: \n  html:\n    code-fold: true\n    page-layout: custom\n    fig-align: center\n    fig-width: 12\n    fig-height: 4\nexecute: \n  message: false\n  warning: false\n  echo: false\nparams:\n  state: \"Oklahoma\"\n  branch: \"dev\"\n---\n\n::: {.cell}\n\n:::\n\n\n\n::::: {.column-body-custom}\n\n:::: {.columns}\n::: {.column width=\"80%\"}\n\n\n<span style='font-family:Playfair Display;font-size:36px;'>As of August 7th, the forecast indicates that it's **unclear whether Kamala Harris or Donald Trump will win** in Nebraska CD-2.</span>\n\n\n:::\n::: {.column width=\"20%\"}\n:::\n::::\n\n---\n\n:::: {.columns}\n::: {.column width=\"60%\"}\n\n\n### <span style='font-family:Playfair Display;'>Presidential probabilities</span>\nEach day, the model simulates thousands of plausible election results, from landslide victories to tightly contested races.\nEach candidate’s probability of winning is the proportion of simulations that they’ve won.\n\n\n:::\n::: {.column width=\"40%\"}\n:::\n::::\n\n\n\n::: {.cell}\n::: {.cell-output-display}\n\n```{=html}\n<div class=\"girafe html-widget html-fill-item\" id=\"htmlwidget-580b6594b6b1c40dffea\" style=\"width:100%;height:216px;\"></div>\n<script type=\"application/json\" data-for=\"htmlwidget-580b6594b6b1c40dffea\">{\"x\":{\"html\":\"<?xml version=\\\"1.0\\\" encoding=\\\"UTF-8\\\"?>\\n<svg xmlns='http://www.w3.org/2000/svg' xmlns:xlink='http://www.w3.org/1999/xlink' class='ggiraph-svg' role='graphics-document' id='svg_1fede6e3_1de4_4f75_a69e_4be663860eb6' viewBox='0 0 864 288'>\\n <defs id='svg_1fede6e3_1de4_4f75_a69e_4be663860eb6_defs'>\\n  <clipPath id='svg_1fede6e3_1de4_4f75_a69e_4be663860eb6_c1'>\\n   <rect x='0' y='0' width='864' height='288'/>\\n  <\\/clipPath>\\n  <clipPath id='svg_1fede6e3_1de4_4f75_a69e_4be663860eb6_c2'>\\n   <rect x='5.98' y='5.98' width='852.04' height='276.04'/>\\n  <\\/clipPath>\\n <\\/defs>\\n <g id='svg_1fede6e3_1de4_4f75_a69e_4be663860eb6_rootg' class='ggiraph-svg-rootg'>\\n  <g clip-path='url(#svg_1fede6e3_1de4_4f75_a69e_4be663860eb6_c1)'>\\n   <rect x='0' y='0' width='864' height='288' fill='#FFFFFF' fill-opacity='1' stroke='#FFFFFF' stroke-opacity='1' stroke-width='0.75' stroke-linejoin='round' stroke-linecap='round' class='ggiraph-svg-bg'/>\\n   <rect x='0' y='0' width='864' height='288' fill='#FFFFFF' fill-opacity='1' stroke='#FFFFFF' stroke-opacity='1' stroke-width='1.16' stroke-linejoin='round' stroke-linecap='round'/>\\n  <\\/g>\\n  <g clip-path='url(#svg_1fede6e3_1de4_4f75_a69e_4be663860eb6_c2)'>\\n   <polyline points='5.98,269.47 858.02,269.47' fill='none' stroke='#EBEBEB' stroke-opacity='1' stroke-width='0.53' stroke-linejoin='round' stroke-linecap='butt'/>\\n   <polyline points='5.98,211.28 858.02,211.28' fill='none' stroke='#EBEBEB' stroke-opacity='1' stroke-width='0.53' stroke-linejoin='round' stroke-linecap='butt'/>\\n   <polyline points='5.98,153.09 858.02,153.09' fill='none' stroke='#EBEBEB' stroke-opacity='1' stroke-width='0.53' stroke-linejoin='round' stroke-linecap='butt'/>\\n   <polyline points='5.98,94.89 858.02,94.89' fill='none' stroke='#EBEBEB' stroke-opacity='1' stroke-width='0.53' stroke-linejoin='round' stroke-linecap='butt'/>\\n   <polyline points='5.98,36.70 858.02,36.70' fill='none' stroke='#EBEBEB' stroke-opacity='1' stroke-width='0.53' stroke-linejoin='round' stroke-linecap='butt'/>\\n  <\\/g>\\n  <g clip-path='url(#svg_1fede6e3_1de4_4f75_a69e_4be663860eb6_c1)'>\\n   <polyline points='94.91,272.46 94.91,269.47' fill='none' stroke='#000000' stroke-opacity='1' stroke-width='1.16' stroke-linejoin='round' stroke-linecap='butt'/>\\n   <polyline points='317.25,272.46 317.25,269.47' fill='none' stroke='#000000' stroke-opacity='1' stroke-width='1.16' stroke-linejoin='round' stroke-linecap='butt'/>\\n   <polyline points='532.41,272.46 532.41,269.47' fill='none' stroke='#000000' stroke-opacity='1' stroke-width='1.16' stroke-linejoin='round' stroke-linecap='butt'/>\\n   <polyline points='754.74,272.46 754.74,269.47' fill='none' stroke='#000000' stroke-opacity='1' stroke-width='1.16' stroke-linejoin='round' stroke-linecap='butt'/>\\n   <text x='79.83' y='281.55' font-size='7.2pt' font-family='IBM Plex Sans' fill='#363A3C' fill-opacity='1'>August<\\/text>\\n   <text x='293.37' y='281.55' font-size='7.2pt' font-family='IBM Plex Sans' fill='#363A3C' fill-opacity='1'>September<\\/text>\\n   <text x='515.06' y='281.55' font-size='7.2pt' font-family='IBM Plex Sans' fill='#363A3C' fill-opacity='1'>October<\\/text>\\n   <text x='732.32' y='281.55' font-size='7.2pt' font-family='IBM Plex Sans' fill='#363A3C' fill-opacity='1'>November<\\/text>\\n   <text x='11.36' y='263.08' font-size='7.2pt' font-family='IBM Plex Sans' fill='#363A3C' fill-opacity='1'>0%<\\/text>\\n   <text x='11.36' y='204.89' font-size='7.2pt' font-family='IBM Plex Sans' fill='#363A3C' fill-opacity='1'>25%<\\/text>\\n   <text x='11.36' y='146.69' font-size='7.2pt' font-family='IBM Plex Sans' fill='#363A3C' fill-opacity='1'>50%<\\/text>\\n   <text x='11.36' y='88.5' font-size='7.2pt' font-family='IBM Plex Sans' fill='#363A3C' fill-opacity='1'>75%<\\/text>\\n   <text x='11.36' y='30.3' font-size='7.2pt' font-family='IBM Plex Sans' fill='#363A3C' fill-opacity='1'>100%<\\/text>\\n  <\\/g>\\n  <g clip-path='url(#svg_1fede6e3_1de4_4f75_a69e_4be663860eb6_c2)'>\\n   <line x1='5.98' y1='269.47' x2='858.02' y2='269.47' stroke='#363A3C' stroke-opacity='1' stroke-width='0.64' stroke-linejoin='round' stroke-linecap='butt'/>\\n   <line x1='5.98' y1='153.09' x2='858.02' y2='153.09' stroke='#363A3C' stroke-opacity='1' stroke-width='0.64' stroke-linejoin='round' stroke-linecap='butt'/>\\n   <line x1='783.43' y1='269.47' x2='783.43' y2='27.18' stroke='#333333' stroke-opacity='1' stroke-width='0.85' stroke-linejoin='round' stroke-linecap='butt'/>\\n   <polygon points='783.43,30.22 786.07,25.66 780.80,25.66' fill='#333333' fill-opacity='1' stroke='#333333' stroke-opacity='1' stroke-width='0.71' stroke-linejoin='round' stroke-linecap='round'/>\\n   <text x='755.69' y='22' font-size='7.47pt' font-family='IBM Plex Sans' fill='#333333' fill-opacity='1'>Election Day<\\/text>\\n   <line x1='137.94' y1='269.47' x2='137.94' y2='36.7' stroke='#333333' stroke-opacity='1' stroke-width='0.85' stroke-linejoin='round' stroke-linecap='butt'/>\\n   <polygon points='137.94,39.74 140.58,35.18 135.31,35.18' fill='#333333' fill-opacity='1' stroke='#333333' stroke-opacity='1' stroke-width='0.71' stroke-linejoin='round' stroke-linecap='round'/>\\n   <text x='115.5' y='29.85' font-size='7.47pt' font-family='IBM Plex Sans' fill='#FFFFFF' fill-opacity='1'>August 7th<\\/text>\\n   <text x='115.05' y='29.18' font-size='7.47pt' font-family='IBM Plex Sans' fill='#FFFFFF' fill-opacity='1'>August 7th<\\/text>\\n   <text x='114.37' y='28.73' font-size='7.47pt' font-family='IBM Plex Sans' fill='#FFFFFF' fill-opacity='1'>August 7th<\\/text>\\n   <text x='113.58' y='28.57' font-size='7.47pt' font-family='IBM Plex Sans' fill='#FFFFFF' fill-opacity='1'>August 7th<\\/text>\\n   <text x='112.78' y='28.73' font-size='7.47pt' font-family='IBM Plex Sans' fill='#FFFFFF' fill-opacity='1'>August 7th<\\/text>\\n   <text x='112.1' y='29.18' font-size='7.47pt' font-family='IBM Plex Sans' fill='#FFFFFF' fill-opacity='1'>August 7th<\\/text>\\n   <text x='111.65' y='29.85' font-size='7.47pt' font-family='IBM Plex Sans' fill='#FFFFFF' fill-opacity='1'>August 7th<\\/text>\\n   <text x='111.49' y='30.65' font-size='7.47pt' font-family='IBM Plex Sans' fill='#FFFFFF' fill-opacity='1'>August 7th<\\/text>\\n   <text x='111.65' y='31.45' font-size='7.47pt' font-family='IBM Plex Sans' fill='#FFFFFF' fill-opacity='1'>August 7th<\\/text>\\n   <text x='112.1' y='32.13' font-size='7.47pt' font-family='IBM Plex Sans' fill='#FFFFFF' fill-opacity='1'>August 7th<\\/text>\\n   <text x='112.78' y='32.58' font-size='7.47pt' font-family='IBM Plex Sans' fill='#FFFFFF' fill-opacity='1'>August 7th<\\/text>\\n   <text x='113.58' y='32.74' font-size='7.47pt' font-family='IBM Plex Sans' fill='#FFFFFF' fill-opacity='1'>August 7th<\\/text>\\n   <text x='114.37' y='32.58' font-size='7.47pt' font-family='IBM Plex Sans' fill='#FFFFFF' fill-opacity='1'>August 7th<\\/text>\\n   <text x='115.05' y='32.13' font-size='7.47pt' font-family='IBM Plex Sans' fill='#FFFFFF' fill-opacity='1'>August 7th<\\/text>\\n   <text x='115.5' y='31.45' font-size='7.47pt' font-family='IBM Plex Sans' fill='#FFFFFF' fill-opacity='1'>August 7th<\\/text>\\n   <text x='115.66' y='30.65' font-size='7.47pt' font-family='IBM Plex Sans' fill='#FFFFFF' fill-opacity='1'>August 7th<\\/text>\\n   <text x='113.58' y='30.65' font-size='7.47pt' font-family='IBM Plex Sans' fill='#333333' fill-opacity='1'>August 7th<\\/text>\\n   <polyline points='94.91,135.74 102.08,133.86 109.26,137.23 116.43,138.10 123.60,139.17 130.77,141.07 137.94,141.31' fill='none' stroke='#FFFFFF' stroke-opacity='1' stroke-width='5.33' stroke-linejoin='round' stroke-linecap='butt'/>\\n   <polyline points='94.91,135.74 102.08,133.86 109.26,137.23 116.43,138.10 123.60,139.17 130.77,141.07 137.94,141.31' fill='none' stroke='#B13737' stroke-opacity='1' stroke-width='1.71' stroke-linejoin='round' stroke-linecap='butt'/>\\n   <polyline points='94.91,170.43 102.08,172.31 109.26,168.94 116.43,168.08 123.60,167.01 130.77,165.10 137.94,164.86' fill='none' stroke='#FFFFFF' stroke-opacity='1' stroke-width='5.33' stroke-linejoin='round' stroke-linecap='butt'/>\\n   <polyline points='94.91,170.43 102.08,172.31 109.26,168.94 116.43,168.08 123.60,167.01 130.77,165.10 137.94,164.86' fill='none' stroke='#3579AC' stroke-opacity='1' stroke-width='1.71' stroke-linejoin='round' stroke-linecap='butt'/>\\n   <circle cx='137.94' cy='141.31' r='2.27pt' fill='#B13737' fill-opacity='1' stroke='#B13737' stroke-opacity='1' stroke-width='0.71' stroke-linejoin='round' stroke-linecap='round'/>\\n   <circle cx='137.94' cy='164.86' r='2.27pt' fill='#3579AC' fill-opacity='1' stroke='#3579AC' stroke-opacity='1' stroke-width='0.71' stroke-linejoin='round' stroke-linecap='round'/>\\n   <text x='153.7' y='128.01' font-size='10.67pt' font-weight='bold' font-family='IBM Plex Sans' fill='#FFFFFF' fill-opacity='1'>Trump<\\/text>\\n   <text x='160.18' y='148.5' font-size='10.67pt' font-weight='bold' font-family='IBM Plex Sans' fill='#FFFFFF' fill-opacity='1'>55%<\\/text>\\n   <text x='153.27' y='127.37' font-size='10.67pt' font-weight='bold' font-family='IBM Plex Sans' fill='#FFFFFF' fill-opacity='1'>Trump<\\/text>\\n   <text x='159.75' y='147.85' font-size='10.67pt' font-weight='bold' font-family='IBM Plex Sans' fill='#FFFFFF' fill-opacity='1'>55%<\\/text>\\n   <text x='152.62' y='126.94' font-size='10.67pt' font-weight='bold' font-family='IBM Plex Sans' fill='#FFFFFF' fill-opacity='1'>Trump<\\/text>\\n   <text x='159.11' y='147.42' font-size='10.67pt' font-weight='bold' font-family='IBM Plex Sans' fill='#FFFFFF' fill-opacity='1'>55%<\\/text>\\n   <text x='151.86' y='126.78' font-size='10.67pt' font-weight='bold' font-family='IBM Plex Sans' fill='#FFFFFF' fill-opacity='1'>Trump<\\/text>\\n   <text x='158.35' y='147.27' font-size='10.67pt' font-weight='bold' font-family='IBM Plex Sans' fill='#FFFFFF' fill-opacity='1'>55%<\\/text>\\n   <text x='151.1' y='126.94' font-size='10.67pt' font-weight='bold' font-family='IBM Plex Sans' fill='#FFFFFF' fill-opacity='1'>Trump<\\/text>\\n   <text x='157.59' y='147.42' font-size='10.67pt' font-weight='bold' font-family='IBM Plex Sans' fill='#FFFFFF' fill-opacity='1'>55%<\\/text>\\n   <text x='150.46' y='127.37' font-size='10.67pt' font-weight='bold' font-family='IBM Plex Sans' fill='#FFFFFF' fill-opacity='1'>Trump<\\/text>\\n   <text x='156.94' y='147.85' font-size='10.67pt' font-weight='bold' font-family='IBM Plex Sans' fill='#FFFFFF' fill-opacity='1'>55%<\\/text>\\n   <text x='150.03' y='128.01' font-size='10.67pt' font-weight='bold' font-family='IBM Plex Sans' fill='#FFFFFF' fill-opacity='1'>Trump<\\/text>\\n   <text x='156.51' y='148.5' font-size='10.67pt' font-weight='bold' font-family='IBM Plex Sans' fill='#FFFFFF' fill-opacity='1'>55%<\\/text>\\n   <text x='149.88' y='128.77' font-size='10.67pt' font-weight='bold' font-family='IBM Plex Sans' fill='#FFFFFF' fill-opacity='1'>Trump<\\/text>\\n   <text x='156.36' y='149.26' font-size='10.67pt' font-weight='bold' font-family='IBM Plex Sans' fill='#FFFFFF' fill-opacity='1'>55%<\\/text>\\n   <text x='150.03' y='129.53' font-size='10.67pt' font-weight='bold' font-family='IBM Plex Sans' fill='#FFFFFF' fill-opacity='1'>Trump<\\/text>\\n   <text x='156.51' y='150.02' font-size='10.67pt' font-weight='bold' font-family='IBM Plex Sans' fill='#FFFFFF' fill-opacity='1'>55%<\\/text>\\n   <text x='150.46' y='130.17' font-size='10.67pt' font-weight='bold' font-family='IBM Plex Sans' fill='#FFFFFF' fill-opacity='1'>Trump<\\/text>\\n   <text x='156.94' y='150.66' font-size='10.67pt' font-weight='bold' font-family='IBM Plex Sans' fill='#FFFFFF' fill-opacity='1'>55%<\\/text>\\n   <text x='151.1' y='130.6' font-size='10.67pt' font-weight='bold' font-family='IBM Plex Sans' fill='#FFFFFF' fill-opacity='1'>Trump<\\/text>\\n   <text x='157.59' y='151.09' font-size='10.67pt' font-weight='bold' font-family='IBM Plex Sans' fill='#FFFFFF' fill-opacity='1'>55%<\\/text>\\n   <text x='151.86' y='130.76' font-size='10.67pt' font-weight='bold' font-family='IBM Plex Sans' fill='#FFFFFF' fill-opacity='1'>Trump<\\/text>\\n   <text x='158.35' y='151.24' font-size='10.67pt' font-weight='bold' font-family='IBM Plex Sans' fill='#FFFFFF' fill-opacity='1'>55%<\\/text>\\n   <text x='152.62' y='130.6' font-size='10.67pt' font-weight='bold' font-family='IBM Plex Sans' fill='#FFFFFF' fill-opacity='1'>Trump<\\/text>\\n   <text x='159.11' y='151.09' font-size='10.67pt' font-weight='bold' font-family='IBM Plex Sans' fill='#FFFFFF' fill-opacity='1'>55%<\\/text>\\n   <text x='153.27' y='130.17' font-size='10.67pt' font-weight='bold' font-family='IBM Plex Sans' fill='#FFFFFF' fill-opacity='1'>Trump<\\/text>\\n   <text x='159.75' y='150.66' font-size='10.67pt' font-weight='bold' font-family='IBM Plex Sans' fill='#FFFFFF' fill-opacity='1'>55%<\\/text>\\n   <text x='153.7' y='129.53' font-size='10.67pt' font-weight='bold' font-family='IBM Plex Sans' fill='#FFFFFF' fill-opacity='1'>Trump<\\/text>\\n   <text x='160.18' y='150.02' font-size='10.67pt' font-weight='bold' font-family='IBM Plex Sans' fill='#FFFFFF' fill-opacity='1'>55%<\\/text>\\n   <text x='153.85' y='128.77' font-size='10.67pt' font-weight='bold' font-family='IBM Plex Sans' fill='#FFFFFF' fill-opacity='1'>Trump<\\/text>\\n   <text x='160.33' y='149.26' font-size='10.67pt' font-weight='bold' font-family='IBM Plex Sans' fill='#FFFFFF' fill-opacity='1'>55%<\\/text>\\n   <text x='151.86' y='128.77' font-size='10.67pt' font-weight='bold' font-family='IBM Plex Sans' fill='#B13737' fill-opacity='1'>Trump<\\/text>\\n   <text x='158.35' y='149.26' font-size='10.67pt' font-weight='bold' font-family='IBM Plex Sans' fill='#B13737' fill-opacity='1'>55%<\\/text>\\n   <text x='155.08' y='166.09' font-size='10.67pt' font-weight='bold' font-family='IBM Plex Sans' fill='#FFFFFF' fill-opacity='1'>Harris<\\/text>\\n   <text x='160.18' y='186.57' font-size='10.67pt' font-weight='bold' font-family='IBM Plex Sans' fill='#FFFFFF' fill-opacity='1'>45%<\\/text>\\n   <text x='154.65' y='165.44' font-size='10.67pt' font-weight='bold' font-family='IBM Plex Sans' fill='#FFFFFF' fill-opacity='1'>Harris<\\/text>\\n   <text x='159.75' y='185.93' font-size='10.67pt' font-weight='bold' font-family='IBM Plex Sans' fill='#FFFFFF' fill-opacity='1'>45%<\\/text>\\n   <text x='154.01' y='165.01' font-size='10.67pt' font-weight='bold' font-family='IBM Plex Sans' fill='#FFFFFF' fill-opacity='1'>Harris<\\/text>\\n   <text x='159.11' y='185.5' font-size='10.67pt' font-weight='bold' font-family='IBM Plex Sans' fill='#FFFFFF' fill-opacity='1'>45%<\\/text>\\n   <text x='153.25' y='164.86' font-size='10.67pt' font-weight='bold' font-family='IBM Plex Sans' fill='#FFFFFF' fill-opacity='1'>Harris<\\/text>\\n   <text x='158.35' y='185.35' font-size='10.67pt' font-weight='bold' font-family='IBM Plex Sans' fill='#FFFFFF' fill-opacity='1'>45%<\\/text>\\n   <text x='152.49' y='165.01' font-size='10.67pt' font-weight='bold' font-family='IBM Plex Sans' fill='#FFFFFF' fill-opacity='1'>Harris<\\/text>\\n   <text x='157.59' y='185.5' font-size='10.67pt' font-weight='bold' font-family='IBM Plex Sans' fill='#FFFFFF' fill-opacity='1'>45%<\\/text>\\n   <text x='151.84' y='165.44' font-size='10.67pt' font-weight='bold' font-family='IBM Plex Sans' fill='#FFFFFF' fill-opacity='1'>Harris<\\/text>\\n   <text x='156.94' y='185.93' font-size='10.67pt' font-weight='bold' font-family='IBM Plex Sans' fill='#FFFFFF' fill-opacity='1'>45%<\\/text>\\n   <text x='151.41' y='166.09' font-size='10.67pt' font-weight='bold' font-family='IBM Plex Sans' fill='#FFFFFF' fill-opacity='1'>Harris<\\/text>\\n   <text x='156.51' y='186.57' font-size='10.67pt' font-weight='bold' font-family='IBM Plex Sans' fill='#FFFFFF' fill-opacity='1'>45%<\\/text>\\n   <text x='151.26' y='166.85' font-size='10.67pt' font-weight='bold' font-family='IBM Plex Sans' fill='#FFFFFF' fill-opacity='1'>Harris<\\/text>\\n   <text x='156.36' y='187.33' font-size='10.67pt' font-weight='bold' font-family='IBM Plex Sans' fill='#FFFFFF' fill-opacity='1'>45%<\\/text>\\n   <text x='151.41' y='167.61' font-size='10.67pt' font-weight='bold' font-family='IBM Plex Sans' fill='#FFFFFF' fill-opacity='1'>Harris<\\/text>\\n   <text x='156.51' y='188.09' font-size='10.67pt' font-weight='bold' font-family='IBM Plex Sans' fill='#FFFFFF' fill-opacity='1'>45%<\\/text>\\n   <text x='151.84' y='168.25' font-size='10.67pt' font-weight='bold' font-family='IBM Plex Sans' fill='#FFFFFF' fill-opacity='1'>Harris<\\/text>\\n   <text x='156.94' y='188.74' font-size='10.67pt' font-weight='bold' font-family='IBM Plex Sans' fill='#FFFFFF' fill-opacity='1'>45%<\\/text>\\n   <text x='152.49' y='168.68' font-size='10.67pt' font-weight='bold' font-family='IBM Plex Sans' fill='#FFFFFF' fill-opacity='1'>Harris<\\/text>\\n   <text x='157.59' y='189.17' font-size='10.67pt' font-weight='bold' font-family='IBM Plex Sans' fill='#FFFFFF' fill-opacity='1'>45%<\\/text>\\n   <text x='153.25' y='168.83' font-size='10.67pt' font-weight='bold' font-family='IBM Plex Sans' fill='#FFFFFF' fill-opacity='1'>Harris<\\/text>\\n   <text x='158.35' y='189.32' font-size='10.67pt' font-weight='bold' font-family='IBM Plex Sans' fill='#FFFFFF' fill-opacity='1'>45%<\\/text>\\n   <text x='154.01' y='168.68' font-size='10.67pt' font-weight='bold' font-family='IBM Plex Sans' fill='#FFFFFF' fill-opacity='1'>Harris<\\/text>\\n   <text x='159.11' y='189.17' font-size='10.67pt' font-weight='bold' font-family='IBM Plex Sans' fill='#FFFFFF' fill-opacity='1'>45%<\\/text>\\n   <text x='154.65' y='168.25' font-size='10.67pt' font-weight='bold' font-family='IBM Plex Sans' fill='#FFFFFF' fill-opacity='1'>Harris<\\/text>\\n   <text x='159.75' y='188.74' font-size='10.67pt' font-weight='bold' font-family='IBM Plex Sans' fill='#FFFFFF' fill-opacity='1'>45%<\\/text>\\n   <text x='155.08' y='167.61' font-size='10.67pt' font-weight='bold' font-family='IBM Plex Sans' fill='#FFFFFF' fill-opacity='1'>Harris<\\/text>\\n   <text x='160.18' y='188.09' font-size='10.67pt' font-weight='bold' font-family='IBM Plex Sans' fill='#FFFFFF' fill-opacity='1'>45%<\\/text>\\n   <text x='155.23' y='166.85' font-size='10.67pt' font-weight='bold' font-family='IBM Plex Sans' fill='#FFFFFF' fill-opacity='1'>Harris<\\/text>\\n   <text x='160.33' y='187.33' font-size='10.67pt' font-weight='bold' font-family='IBM Plex Sans' fill='#FFFFFF' fill-opacity='1'>45%<\\/text>\\n   <text x='153.25' y='166.85' font-size='10.67pt' font-weight='bold' font-family='IBM Plex Sans' fill='#3579AC' fill-opacity='1'>Harris<\\/text>\\n   <text x='158.35' y='187.33' font-size='10.67pt' font-weight='bold' font-family='IBM Plex Sans' fill='#3579AC' fill-opacity='1'>45%<\\/text>\\n   <rect id='svg_1fede6e3_1de4_4f75_a69e_4be663860eb6_e1' x='91.33' y='36.7' width='7.17' height='232.78' fill='#333333' fill-opacity='0' stroke='none' title='August 1st&amp;lt;br&amp;gt;Harris: &amp;lt;span style=&amp;#39;float:right;&amp;#39;&amp;gt;43%&amp;lt;/span&amp;gt;&amp;lt;br&amp;gt;Trump: &amp;lt;span style=&amp;#39;float:right;&amp;#39;&amp;gt;57%&amp;lt;/span&amp;gt;'/>\\n   <rect id='svg_1fede6e3_1de4_4f75_a69e_4be663860eb6_e2' x='98.5' y='36.7' width='7.17' height='232.78' fill='#333333' fill-opacity='0' stroke='none' title='August 2nd&amp;lt;br&amp;gt;Harris: &amp;lt;span style=&amp;#39;float:right;&amp;#39;&amp;gt;42%&amp;lt;/span&amp;gt;&amp;lt;br&amp;gt;Trump: &amp;lt;span style=&amp;#39;float:right;&amp;#39;&amp;gt;58%&amp;lt;/span&amp;gt;'/>\\n   <rect id='svg_1fede6e3_1de4_4f75_a69e_4be663860eb6_e3' x='105.67' y='36.7' width='7.17' height='232.78' fill='#333333' fill-opacity='0' stroke='none' title='August 3rd&amp;lt;br&amp;gt;Harris: &amp;lt;span style=&amp;#39;float:right;&amp;#39;&amp;gt;43%&amp;lt;/span&amp;gt;&amp;lt;br&amp;gt;Trump: &amp;lt;span style=&amp;#39;float:right;&amp;#39;&amp;gt;57%&amp;lt;/span&amp;gt;'/>\\n   <rect id='svg_1fede6e3_1de4_4f75_a69e_4be663860eb6_e4' x='112.84' y='36.7' width='7.17' height='232.78' fill='#333333' fill-opacity='0' stroke='none' title='August 4th&amp;lt;br&amp;gt;Harris: &amp;lt;span style=&amp;#39;float:right;&amp;#39;&amp;gt;44%&amp;lt;/span&amp;gt;&amp;lt;br&amp;gt;Trump: &amp;lt;span style=&amp;#39;float:right;&amp;#39;&amp;gt;56%&amp;lt;/span&amp;gt;'/>\\n   <rect id='svg_1fede6e3_1de4_4f75_a69e_4be663860eb6_e5' x='120.01' y='36.7' width='7.17' height='232.78' fill='#333333' fill-opacity='0' stroke='none' title='August 5th&amp;lt;br&amp;gt;Harris: &amp;lt;span style=&amp;#39;float:right;&amp;#39;&amp;gt;44%&amp;lt;/span&amp;gt;&amp;lt;br&amp;gt;Trump: &amp;lt;span style=&amp;#39;float:right;&amp;#39;&amp;gt;56%&amp;lt;/span&amp;gt;'/>\\n   <rect id='svg_1fede6e3_1de4_4f75_a69e_4be663860eb6_e6' x='127.19' y='36.7' width='7.17' height='232.78' fill='#333333' fill-opacity='0' stroke='none' title='August 6th&amp;lt;br&amp;gt;Harris: &amp;lt;span style=&amp;#39;float:right;&amp;#39;&amp;gt;45%&amp;lt;/span&amp;gt;&amp;lt;br&amp;gt;Trump: &amp;lt;span style=&amp;#39;float:right;&amp;#39;&amp;gt;55%&amp;lt;/span&amp;gt;'/>\\n   <rect id='svg_1fede6e3_1de4_4f75_a69e_4be663860eb6_e7' x='134.36' y='36.7' width='7.17' height='232.78' fill='#333333' fill-opacity='0' stroke='none' title='August 7th&amp;lt;br&amp;gt;Harris: &amp;lt;span style=&amp;#39;float:right;&amp;#39;&amp;gt;45%&amp;lt;/span&amp;gt;&amp;lt;br&amp;gt;Trump: &amp;lt;span style=&amp;#39;float:right;&amp;#39;&amp;gt;55%&amp;lt;/span&amp;gt;'/>\\n  <\\/g>\\n <\\/g>\\n<\\/svg>\",\"js\":null,\"uid\":\"svg_1fede6e3_1de4_4f75_a69e_4be663860eb6\",\"ratio\":3,\"settings\":{\"tooltip\":{\"css\":\".tooltip_SVGID_ { font-family:IBM Plex Sans;color:#363a3c;background-color:#fafafa;padding:5px;border-radius:3px;border-color:black;border-style:solid;border-width:0.125em 0em 0em 0em;box-shadow: 0px 0px 10px 5px lightgray;min-width: 120px ; position:absolute;pointer-events:none;z-index:999;}\",\"placement\":\"doc\",\"opacity\":1,\"offx\":10,\"offy\":0,\"use_cursor_pos\":true,\"use_fill\":false,\"use_stroke\":false,\"delay_over\":200,\"delay_out\":500},\"hover\":{\"css\":\".hover_data_SVGID_ { fill:orange;stroke:black;cursor:pointer; }\\ntext.hover_data_SVGID_ { stroke:none;fill:orange; }\\ncircle.hover_data_SVGID_ { fill:orange;stroke:black; }\\nline.hover_data_SVGID_, polyline.hover_data_SVGID_ { fill:none;stroke:orange; }\\nrect.hover_data_SVGID_, polygon.hover_data_SVGID_, path.hover_data_SVGID_ { fill:orange;stroke:none; }\\nimage.hover_data_SVGID_ { stroke:orange; }\",\"reactive\":true,\"nearest_distance\":null},\"hover_inv\":{\"css\":\"\"},\"hover_key\":{\"css\":\".hover_key_SVGID_ { fill:orange;stroke:black;cursor:pointer; }\\ntext.hover_key_SVGID_ { stroke:none;fill:orange; }\\ncircle.hover_key_SVGID_ { fill:orange;stroke:black; }\\nline.hover_key_SVGID_, polyline.hover_key_SVGID_ { fill:none;stroke:orange; }\\nrect.hover_key_SVGID_, polygon.hover_key_SVGID_, path.hover_key_SVGID_ { fill:orange;stroke:none; }\\nimage.hover_key_SVGID_ { stroke:orange; }\",\"reactive\":true},\"hover_theme\":{\"css\":\".hover_theme_SVGID_ { fill:orange;stroke:black;cursor:pointer; }\\ntext.hover_theme_SVGID_ { stroke:none;fill:orange; }\\ncircle.hover_theme_SVGID_ { fill:orange;stroke:black; }\\nline.hover_theme_SVGID_, polyline.hover_theme_SVGID_ { fill:none;stroke:orange; }\\nrect.hover_theme_SVGID_, polygon.hover_theme_SVGID_, path.hover_theme_SVGID_ { fill:orange;stroke:none; }\\nimage.hover_theme_SVGID_ { stroke:orange; }\",\"reactive\":true},\"select\":{\"css\":\".select_data_SVGID_ { fill:red;stroke:black;cursor:pointer; }\\ntext.select_data_SVGID_ { stroke:none;fill:red; }\\ncircle.select_data_SVGID_ { fill:red;stroke:black; }\\nline.select_data_SVGID_, polyline.select_data_SVGID_ { fill:none;stroke:red; }\\nrect.select_data_SVGID_, polygon.select_data_SVGID_, path.select_data_SVGID_ { fill:red;stroke:none; }\\nimage.select_data_SVGID_ { stroke:red; }\",\"type\":\"multiple\",\"only_shiny\":true,\"selected\":[]},\"select_inv\":{\"css\":\"\"},\"select_key\":{\"css\":\".select_key_SVGID_ { fill:red;stroke:black;cursor:pointer; }\\ntext.select_key_SVGID_ { stroke:none;fill:red; }\\ncircle.select_key_SVGID_ { fill:red;stroke:black; }\\nline.select_key_SVGID_, polyline.select_key_SVGID_ { fill:none;stroke:red; }\\nrect.select_key_SVGID_, polygon.select_key_SVGID_, path.select_key_SVGID_ { fill:red;stroke:none; }\\nimage.select_key_SVGID_ { stroke:red; }\",\"type\":\"single\",\"only_shiny\":true,\"selected\":[]},\"select_theme\":{\"css\":\".select_theme_SVGID_ { fill:red;stroke:black;cursor:pointer; }\\ntext.select_theme_SVGID_ { stroke:none;fill:red; }\\ncircle.select_theme_SVGID_ { fill:red;stroke:black; }\\nline.select_theme_SVGID_, polyline.select_theme_SVGID_ { fill:none;stroke:red; }\\nrect.select_theme_SVGID_, polygon.select_theme_SVGID_, path.select_theme_SVGID_ { fill:red;stroke:none; }\\nimage.select_theme_SVGID_ { stroke:red; }\",\"type\":\"single\",\"only_shiny\":true,\"selected\":[]},\"zoom\":{\"min\":1,\"max\":1,\"duration\":300},\"toolbar\":{\"position\":\"topright\",\"pngname\":\"diagram\",\"tooltips\":null,\"fixed\":false,\"hidden\":[],\"delay_over\":200,\"delay_out\":500},\"sizing\":{\"rescale\":true,\"width\":1}}},\"evals\":[],\"jsHooks\":[]}</script>\n```\n\n:::\n:::\n\n\n\n---\n\n:::: {.columns}\n::: {.column width=\"60%\"}\n\n\n### <span style='font-family:Playfair Display;'>Forecasted election-day voteshare</span>\nThe model first constructs a polling average, pooling data across similar states when polls are sparse.\nIt then projects forward to election day, initially relying on non-polling indicators like economic growth and partisanship, but aligning more closely with the polling average as election day approaches.\n\n\n:::\n::: {.column width=\"40%\"}\n:::\n::::\n\n\n\n::: {.cell}\n::: {.cell-output-display}\n\n```{=html}\n<div class=\"girafe html-widget html-fill-item\" id=\"htmlwidget-7e87a69041edc7e16beb\" style=\"width:100%;height:216px;\"></div>\n<script type=\"application/json\" data-for=\"htmlwidget-7e87a69041edc7e16beb\">{\"x\":{\"html\":\"<?xml version=\\\"1.0\\\" encoding=\\\"UTF-8\\\"?>\\n<svg xmlns='http://www.w3.org/2000/svg' xmlns:xlink='http://www.w3.org/1999/xlink' class='ggiraph-svg' role='graphics-document' id='svg_1c198605_0a6c_4f9e_8e95_555ee0d0f554' viewBox='0 0 864 288'>\\n <defs id='svg_1c198605_0a6c_4f9e_8e95_555ee0d0f554_defs'>\\n  <clipPath id='svg_1c198605_0a6c_4f9e_8e95_555ee0d0f554_c1'>\\n   <rect x='0' y='0' width='864' height='288'/>\\n  <\\/clipPath>\\n  <clipPath id='svg_1c198605_0a6c_4f9e_8e95_555ee0d0f554_c2'>\\n   <rect x='5.98' y='5.98' width='852.04' height='276.04'/>\\n  <\\/clipPath>\\n <\\/defs>\\n <g id='svg_1c198605_0a6c_4f9e_8e95_555ee0d0f554_rootg' class='ggiraph-svg-rootg'>\\n  <g clip-path='url(#svg_1c198605_0a6c_4f9e_8e95_555ee0d0f554_c1)'>\\n   <rect x='0' y='0' width='864' height='288' fill='#FFFFFF' fill-opacity='1' stroke='#FFFFFF' stroke-opacity='1' stroke-width='0.75' stroke-linejoin='round' stroke-linecap='round' class='ggiraph-svg-bg'/>\\n   <rect x='0' y='0' width='864' height='288' fill='#FFFFFF' fill-opacity='1' stroke='#FFFFFF' stroke-opacity='1' stroke-width='1.16' stroke-linejoin='round' stroke-linecap='round'/>\\n  <\\/g>\\n  <g clip-path='url(#svg_1c198605_0a6c_4f9e_8e95_555ee0d0f554_c2)'>\\n   <polyline points='5.98,249.37 858.02,249.37' fill='none' stroke='#EBEBEB' stroke-opacity='1' stroke-width='0.53' stroke-linejoin='round' stroke-linecap='butt'/>\\n   <polyline points='5.98,201.23 858.02,201.23' fill='none' stroke='#EBEBEB' stroke-opacity='1' stroke-width='0.53' stroke-linejoin='round' stroke-linecap='butt'/>\\n   <polyline points='5.98,153.09 858.02,153.09' fill='none' stroke='#EBEBEB' stroke-opacity='1' stroke-width='0.53' stroke-linejoin='round' stroke-linecap='butt'/>\\n   <polyline points='5.98,104.94 858.02,104.94' fill='none' stroke='#EBEBEB' stroke-opacity='1' stroke-width='0.53' stroke-linejoin='round' stroke-linecap='butt'/>\\n   <polyline points='5.98,56.80 858.02,56.80' fill='none' stroke='#EBEBEB' stroke-opacity='1' stroke-width='0.53' stroke-linejoin='round' stroke-linecap='butt'/>\\n  <\\/g>\\n  <g clip-path='url(#svg_1c198605_0a6c_4f9e_8e95_555ee0d0f554_c1)'>\\n   <polyline points='94.91,272.46 94.91,269.47' fill='none' stroke='#000000' stroke-opacity='1' stroke-width='1.16' stroke-linejoin='round' stroke-linecap='butt'/>\\n   <polyline points='317.25,272.46 317.25,269.47' fill='none' stroke='#000000' stroke-opacity='1' stroke-width='1.16' stroke-linejoin='round' stroke-linecap='butt'/>\\n   <polyline points='532.41,272.46 532.41,269.47' fill='none' stroke='#000000' stroke-opacity='1' stroke-width='1.16' stroke-linejoin='round' stroke-linecap='butt'/>\\n   <polyline points='754.74,272.46 754.74,269.47' fill='none' stroke='#000000' stroke-opacity='1' stroke-width='1.16' stroke-linejoin='round' stroke-linecap='butt'/>\\n   <text x='79.83' y='281.55' font-size='7.2pt' font-family='IBM Plex Sans' fill='#363A3C' fill-opacity='1'>August<\\/text>\\n   <text x='293.37' y='281.55' font-size='7.2pt' font-family='IBM Plex Sans' fill='#363A3C' fill-opacity='1'>September<\\/text>\\n   <text x='515.06' y='281.55' font-size='7.2pt' font-family='IBM Plex Sans' fill='#363A3C' fill-opacity='1'>October<\\/text>\\n   <text x='732.32' y='281.55' font-size='7.2pt' font-family='IBM Plex Sans' fill='#363A3C' fill-opacity='1'>November<\\/text>\\n   <text x='11.36' y='242.98' font-size='7.2pt' font-family='IBM Plex Sans' fill='#363A3C' fill-opacity='1'>40%<\\/text>\\n   <text x='11.36' y='194.84' font-size='7.2pt' font-family='IBM Plex Sans' fill='#363A3C' fill-opacity='1'>45%<\\/text>\\n   <text x='11.36' y='146.69' font-size='7.2pt' font-family='IBM Plex Sans' fill='#363A3C' fill-opacity='1'>50%<\\/text>\\n   <text x='11.36' y='98.55' font-size='7.2pt' font-family='IBM Plex Sans' fill='#363A3C' fill-opacity='1'>55%<\\/text>\\n   <text x='11.36' y='50.41' font-size='7.2pt' font-family='IBM Plex Sans' fill='#363A3C' fill-opacity='1'>60%<\\/text>\\n  <\\/g>\\n  <g clip-path='url(#svg_1c198605_0a6c_4f9e_8e95_555ee0d0f554_c2)'>\\n   <line x1='5.98' y1='153.09' x2='858.02' y2='153.09' stroke='#363A3C' stroke-opacity='1' stroke-width='0.64' stroke-linejoin='round' stroke-linecap='butt'/>\\n   <polygon points='94.91,65.56 102.08,66.20 109.26,66.36 116.43,68.30 123.60,68.13 130.77,67.98 137.94,69.15 137.94,254.47 130.77,258.89 123.60,250.94 116.43,254.24 109.26,250.80 102.08,250.44 94.91,250.58' fill='#B13737' fill-opacity='0.13' stroke='none'/>\\n   <polyline points='94.91,65.56 102.08,66.20 109.26,66.36 116.43,68.30 123.60,68.13 130.77,67.98 137.94,69.15' fill='none' stroke='none'/>\\n   <polyline points='137.94,254.47 130.77,258.89 123.60,250.94 116.43,254.24 109.26,250.80 102.08,250.44 94.91,250.58' fill='none' stroke='none'/>\\n   <polygon points='94.91,104.60 102.08,104.07 109.26,104.24 116.43,107.18 123.60,106.95 130.77,107.11 137.94,109.09 137.94,193.87 130.77,193.66 123.60,191.86 116.43,191.86 109.26,191.74 102.08,189.13 94.91,190.45' fill='#B13737' fill-opacity='0.13' stroke='none'/>\\n   <polyline points='94.91,104.60 102.08,104.07 109.26,104.24 116.43,107.18 123.60,106.95 130.77,107.11 137.94,109.09' fill='none' stroke='none'/>\\n   <polyline points='137.94,193.87 130.77,193.66 123.60,191.86 116.43,191.86 109.26,191.74 102.08,189.13 94.91,190.45' fill='none' stroke='none'/>\\n   <polygon points='94.91,55.59 102.08,55.74 109.26,55.37 116.43,51.93 123.60,55.23 130.77,47.28 137.94,51.70 137.94,237.03 130.77,238.19 123.60,238.04 116.43,237.88 109.26,239.81 102.08,239.97 94.91,240.61' fill='#3579AC' fill-opacity='0.13' stroke='none'/>\\n   <polyline points='94.91,55.59 102.08,55.74 109.26,55.37 116.43,51.93 123.60,55.23 130.77,47.28 137.94,51.70' fill='none' stroke='none'/>\\n   <polyline points='137.94,237.03 130.77,238.19 123.60,238.04 116.43,237.88 109.26,239.81 102.08,239.97 94.91,240.61' fill='none' stroke='none'/>\\n   <polygon points='94.91,115.72 102.08,117.04 109.26,114.43 116.43,114.31 123.60,114.31 130.77,112.52 137.94,112.30 137.94,197.08 130.77,199.06 123.60,199.23 116.43,198.99 109.26,201.93 102.08,202.10 94.91,201.57' fill='#3579AC' fill-opacity='0.13' stroke='none'/>\\n   <polyline points='94.91,115.72 102.08,117.04 109.26,114.43 116.43,114.31 123.60,114.31 130.77,112.52 137.94,112.30' fill='none' stroke='none'/>\\n   <polyline points='137.94,197.08 130.77,199.06 123.60,199.23 116.43,198.99 109.26,201.93 102.08,202.10 94.91,201.57' fill='none' stroke='none'/>\\n   <line x1='783.43' y1='269.47' x2='783.43' y2='27.18' stroke='#333333' stroke-opacity='1' stroke-width='0.85' stroke-linejoin='round' stroke-linecap='butt'/>\\n   <polygon points='783.43,30.22 786.07,25.66 780.80,25.66' fill='#333333' fill-opacity='1' stroke='#333333' stroke-opacity='1' stroke-width='0.71' stroke-linejoin='round' stroke-linecap='round'/>\\n   <text x='755.69' y='22' font-size='7.47pt' font-family='IBM Plex Sans' fill='#333333' fill-opacity='1'>Election Day<\\/text>\\n   <line x1='137.94' y1='269.47' x2='137.94' y2='36.7' stroke='#333333' stroke-opacity='1' stroke-width='0.85' stroke-linejoin='round' stroke-linecap='butt'/>\\n   <polygon points='137.94,39.74 140.58,35.18 135.31,35.18' fill='#333333' fill-opacity='1' stroke='#333333' stroke-opacity='1' stroke-width='0.71' stroke-linejoin='round' stroke-linecap='round'/>\\n   <text x='115.5' y='29.85' font-size='7.47pt' font-family='IBM Plex Sans' fill='#FFFFFF' fill-opacity='1'>August 7th<\\/text>\\n   <text x='115.05' y='29.18' font-size='7.47pt' font-family='IBM Plex Sans' fill='#FFFFFF' fill-opacity='1'>August 7th<\\/text>\\n   <text x='114.37' y='28.73' font-size='7.47pt' font-family='IBM Plex Sans' fill='#FFFFFF' fill-opacity='1'>August 7th<\\/text>\\n   <text x='113.58' y='28.57' font-size='7.47pt' font-family='IBM Plex Sans' fill='#FFFFFF' fill-opacity='1'>August 7th<\\/text>\\n   <text x='112.78' y='28.73' font-size='7.47pt' font-family='IBM Plex Sans' fill='#FFFFFF' fill-opacity='1'>August 7th<\\/text>\\n   <text x='112.1' y='29.18' font-size='7.47pt' font-family='IBM Plex Sans' fill='#FFFFFF' fill-opacity='1'>August 7th<\\/text>\\n   <text x='111.65' y='29.85' font-size='7.47pt' font-family='IBM Plex Sans' fill='#FFFFFF' fill-opacity='1'>August 7th<\\/text>\\n   <text x='111.49' y='30.65' font-size='7.47pt' font-family='IBM Plex Sans' fill='#FFFFFF' fill-opacity='1'>August 7th<\\/text>\\n   <text x='111.65' y='31.45' font-size='7.47pt' font-family='IBM Plex Sans' fill='#FFFFFF' fill-opacity='1'>August 7th<\\/text>\\n   <text x='112.1' y='32.13' font-size='7.47pt' font-family='IBM Plex Sans' fill='#FFFFFF' fill-opacity='1'>August 7th<\\/text>\\n   <text x='112.78' y='32.58' font-size='7.47pt' font-family='IBM Plex Sans' fill='#FFFFFF' fill-opacity='1'>August 7th<\\/text>\\n   <text x='113.58' y='32.74' font-size='7.47pt' font-family='IBM Plex Sans' fill='#FFFFFF' fill-opacity='1'>August 7th<\\/text>\\n   <text x='114.37' y='32.58' font-size='7.47pt' font-family='IBM Plex Sans' fill='#FFFFFF' fill-opacity='1'>August 7th<\\/text>\\n   <text x='115.05' y='32.13' font-size='7.47pt' font-family='IBM Plex Sans' fill='#FFFFFF' fill-opacity='1'>August 7th<\\/text>\\n   <text x='115.5' y='31.45' font-size='7.47pt' font-family='IBM Plex Sans' fill='#FFFFFF' fill-opacity='1'>August 7th<\\/text>\\n   <text x='115.66' y='30.65' font-size='7.47pt' font-family='IBM Plex Sans' fill='#FFFFFF' fill-opacity='1'>August 7th<\\/text>\\n   <text x='113.58' y='30.65' font-size='7.47pt' font-family='IBM Plex Sans' fill='#333333' fill-opacity='1'>August 7th<\\/text>\\n   <line x1='5.98' y1='269.47' x2='858.02' y2='269.47' stroke='#363A3C' stroke-opacity='1' stroke-width='0.64' stroke-linejoin='round' stroke-linecap='butt'/>\\n   <polyline points='94.91,144.77 102.08,143.35 109.26,145.22 116.43,145.65 123.60,146.72 130.77,147.38 137.94,147.33' fill='none' stroke='#FFFFFF' stroke-opacity='1' stroke-width='5.33' stroke-linejoin='round' stroke-linecap='butt'/>\\n   <polyline points='94.91,144.77 102.08,143.35 109.26,145.22 116.43,145.65 123.60,146.72 130.77,147.38 137.94,147.33' fill='none' stroke='#B13737' stroke-opacity='1' stroke-width='1.71' stroke-linejoin='round' stroke-linecap='butt'/>\\n   <polyline points='94.91,161.41 102.08,162.82 109.26,160.95 116.43,160.52 123.60,159.45 130.77,158.79 137.94,158.84' fill='none' stroke='#FFFFFF' stroke-opacity='1' stroke-width='5.33' stroke-linejoin='round' stroke-linecap='butt'/>\\n   <polyline points='94.91,161.41 102.08,162.82 109.26,160.95 116.43,160.52 123.60,159.45 130.77,158.79 137.94,158.84' fill='none' stroke='#3579AC' stroke-opacity='1' stroke-width='1.71' stroke-linejoin='round' stroke-linecap='butt'/>\\n   <circle cx='137.94' cy='147.33' r='2.27pt' fill='#B13737' fill-opacity='1' stroke='#B13737' stroke-opacity='1' stroke-width='0.71' stroke-linejoin='round' stroke-linecap='round'/>\\n   <circle cx='137.94' cy='158.84' r='2.27pt' fill='#3579AC' fill-opacity='1' stroke='#3579AC' stroke-opacity='1' stroke-width='0.71' stroke-linejoin='round' stroke-linecap='round'/>\\n   <text x='153.7' y='128.01' font-size='10.67pt' font-weight='bold' font-family='IBM Plex Sans' fill='#FFFFFF' fill-opacity='1'>Trump<\\/text>\\n   <text x='153.71' y='148.5' font-size='10.67pt' font-weight='bold' font-family='IBM Plex Sans' fill='#FFFFFF' fill-opacity='1'>50.6%<\\/text>\\n   <text x='153.27' y='127.37' font-size='10.67pt' font-weight='bold' font-family='IBM Plex Sans' fill='#FFFFFF' fill-opacity='1'>Trump<\\/text>\\n   <text x='153.28' y='147.85' font-size='10.67pt' font-weight='bold' font-family='IBM Plex Sans' fill='#FFFFFF' fill-opacity='1'>50.6%<\\/text>\\n   <text x='152.62' y='126.94' font-size='10.67pt' font-weight='bold' font-family='IBM Plex Sans' fill='#FFFFFF' fill-opacity='1'>Trump<\\/text>\\n   <text x='152.64' y='147.42' font-size='10.67pt' font-weight='bold' font-family='IBM Plex Sans' fill='#FFFFFF' fill-opacity='1'>50.6%<\\/text>\\n   <text x='151.86' y='126.78' font-size='10.67pt' font-weight='bold' font-family='IBM Plex Sans' fill='#FFFFFF' fill-opacity='1'>Trump<\\/text>\\n   <text x='151.88' y='147.27' font-size='10.67pt' font-weight='bold' font-family='IBM Plex Sans' fill='#FFFFFF' fill-opacity='1'>50.6%<\\/text>\\n   <text x='151.1' y='126.94' font-size='10.67pt' font-weight='bold' font-family='IBM Plex Sans' fill='#FFFFFF' fill-opacity='1'>Trump<\\/text>\\n   <text x='151.12' y='147.42' font-size='10.67pt' font-weight='bold' font-family='IBM Plex Sans' fill='#FFFFFF' fill-opacity='1'>50.6%<\\/text>\\n   <text x='150.46' y='127.37' font-size='10.67pt' font-weight='bold' font-family='IBM Plex Sans' fill='#FFFFFF' fill-opacity='1'>Trump<\\/text>\\n   <text x='150.47' y='147.85' font-size='10.67pt' font-weight='bold' font-family='IBM Plex Sans' fill='#FFFFFF' fill-opacity='1'>50.6%<\\/text>\\n   <text x='150.03' y='128.01' font-size='10.67pt' font-weight='bold' font-family='IBM Plex Sans' fill='#FFFFFF' fill-opacity='1'>Trump<\\/text>\\n   <text x='150.04' y='148.5' font-size='10.67pt' font-weight='bold' font-family='IBM Plex Sans' fill='#FFFFFF' fill-opacity='1'>50.6%<\\/text>\\n   <text x='149.88' y='128.77' font-size='10.67pt' font-weight='bold' font-family='IBM Plex Sans' fill='#FFFFFF' fill-opacity='1'>Trump<\\/text>\\n   <text x='149.89' y='149.26' font-size='10.67pt' font-weight='bold' font-family='IBM Plex Sans' fill='#FFFFFF' fill-opacity='1'>50.6%<\\/text>\\n   <text x='150.03' y='129.53' font-size='10.67pt' font-weight='bold' font-family='IBM Plex Sans' fill='#FFFFFF' fill-opacity='1'>Trump<\\/text>\\n   <text x='150.04' y='150.02' font-size='10.67pt' font-weight='bold' font-family='IBM Plex Sans' fill='#FFFFFF' fill-opacity='1'>50.6%<\\/text>\\n   <text x='150.46' y='130.17' font-size='10.67pt' font-weight='bold' font-family='IBM Plex Sans' fill='#FFFFFF' fill-opacity='1'>Trump<\\/text>\\n   <text x='150.47' y='150.66' font-size='10.67pt' font-weight='bold' font-family='IBM Plex Sans' fill='#FFFFFF' fill-opacity='1'>50.6%<\\/text>\\n   <text x='151.1' y='130.6' font-size='10.67pt' font-weight='bold' font-family='IBM Plex Sans' fill='#FFFFFF' fill-opacity='1'>Trump<\\/text>\\n   <text x='151.12' y='151.09' font-size='10.67pt' font-weight='bold' font-family='IBM Plex Sans' fill='#FFFFFF' fill-opacity='1'>50.6%<\\/text>\\n   <text x='151.86' y='130.76' font-size='10.67pt' font-weight='bold' font-family='IBM Plex Sans' fill='#FFFFFF' fill-opacity='1'>Trump<\\/text>\\n   <text x='151.88' y='151.24' font-size='10.67pt' font-weight='bold' font-family='IBM Plex Sans' fill='#FFFFFF' fill-opacity='1'>50.6%<\\/text>\\n   <text x='152.62' y='130.6' font-size='10.67pt' font-weight='bold' font-family='IBM Plex Sans' fill='#FFFFFF' fill-opacity='1'>Trump<\\/text>\\n   <text x='152.64' y='151.09' font-size='10.67pt' font-weight='bold' font-family='IBM Plex Sans' fill='#FFFFFF' fill-opacity='1'>50.6%<\\/text>\\n   <text x='153.27' y='130.17' font-size='10.67pt' font-weight='bold' font-family='IBM Plex Sans' fill='#FFFFFF' fill-opacity='1'>Trump<\\/text>\\n   <text x='153.28' y='150.66' font-size='10.67pt' font-weight='bold' font-family='IBM Plex Sans' fill='#FFFFFF' fill-opacity='1'>50.6%<\\/text>\\n   <text x='153.7' y='129.53' font-size='10.67pt' font-weight='bold' font-family='IBM Plex Sans' fill='#FFFFFF' fill-opacity='1'>Trump<\\/text>\\n   <text x='153.71' y='150.02' font-size='10.67pt' font-weight='bold' font-family='IBM Plex Sans' fill='#FFFFFF' fill-opacity='1'>50.6%<\\/text>\\n   <text x='153.85' y='128.77' font-size='10.67pt' font-weight='bold' font-family='IBM Plex Sans' fill='#FFFFFF' fill-opacity='1'>Trump<\\/text>\\n   <text x='153.86' y='149.26' font-size='10.67pt' font-weight='bold' font-family='IBM Plex Sans' fill='#FFFFFF' fill-opacity='1'>50.6%<\\/text>\\n   <text x='151.86' y='128.77' font-size='10.67pt' font-weight='bold' font-family='IBM Plex Sans' fill='#B13737' fill-opacity='1'>Trump<\\/text>\\n   <text x='151.88' y='149.26' font-size='10.67pt' font-weight='bold' font-family='IBM Plex Sans' fill='#B13737' fill-opacity='1'>50.6%<\\/text>\\n   <text x='155.08' y='166.09' font-size='10.67pt' font-weight='bold' font-family='IBM Plex Sans' fill='#FFFFFF' fill-opacity='1'>Harris<\\/text>\\n   <text x='153.71' y='186.57' font-size='10.67pt' font-weight='bold' font-family='IBM Plex Sans' fill='#FFFFFF' fill-opacity='1'>49.4%<\\/text>\\n   <text x='154.65' y='165.44' font-size='10.67pt' font-weight='bold' font-family='IBM Plex Sans' fill='#FFFFFF' fill-opacity='1'>Harris<\\/text>\\n   <text x='153.28' y='185.93' font-size='10.67pt' font-weight='bold' font-family='IBM Plex Sans' fill='#FFFFFF' fill-opacity='1'>49.4%<\\/text>\\n   <text x='154.01' y='165.01' font-size='10.67pt' font-weight='bold' font-family='IBM Plex Sans' fill='#FFFFFF' fill-opacity='1'>Harris<\\/text>\\n   <text x='152.64' y='185.5' font-size='10.67pt' font-weight='bold' font-family='IBM Plex Sans' fill='#FFFFFF' fill-opacity='1'>49.4%<\\/text>\\n   <text x='153.25' y='164.86' font-size='10.67pt' font-weight='bold' font-family='IBM Plex Sans' fill='#FFFFFF' fill-opacity='1'>Harris<\\/text>\\n   <text x='151.88' y='185.35' font-size='10.67pt' font-weight='bold' font-family='IBM Plex Sans' fill='#FFFFFF' fill-opacity='1'>49.4%<\\/text>\\n   <text x='152.49' y='165.01' font-size='10.67pt' font-weight='bold' font-family='IBM Plex Sans' fill='#FFFFFF' fill-opacity='1'>Harris<\\/text>\\n   <text x='151.12' y='185.5' font-size='10.67pt' font-weight='bold' font-family='IBM Plex Sans' fill='#FFFFFF' fill-opacity='1'>49.4%<\\/text>\\n   <text x='151.84' y='165.44' font-size='10.67pt' font-weight='bold' font-family='IBM Plex Sans' fill='#FFFFFF' fill-opacity='1'>Harris<\\/text>\\n   <text x='150.47' y='185.93' font-size='10.67pt' font-weight='bold' font-family='IBM Plex Sans' fill='#FFFFFF' fill-opacity='1'>49.4%<\\/text>\\n   <text x='151.41' y='166.09' font-size='10.67pt' font-weight='bold' font-family='IBM Plex Sans' fill='#FFFFFF' fill-opacity='1'>Harris<\\/text>\\n   <text x='150.04' y='186.57' font-size='10.67pt' font-weight='bold' font-family='IBM Plex Sans' fill='#FFFFFF' fill-opacity='1'>49.4%<\\/text>\\n   <text x='151.26' y='166.85' font-size='10.67pt' font-weight='bold' font-family='IBM Plex Sans' fill='#FFFFFF' fill-opacity='1'>Harris<\\/text>\\n   <text x='149.89' y='187.33' font-size='10.67pt' font-weight='bold' font-family='IBM Plex Sans' fill='#FFFFFF' fill-opacity='1'>49.4%<\\/text>\\n   <text x='151.41' y='167.61' font-size='10.67pt' font-weight='bold' font-family='IBM Plex Sans' fill='#FFFFFF' fill-opacity='1'>Harris<\\/text>\\n   <text x='150.04' y='188.09' font-size='10.67pt' font-weight='bold' font-family='IBM Plex Sans' fill='#FFFFFF' fill-opacity='1'>49.4%<\\/text>\\n   <text x='151.84' y='168.25' font-size='10.67pt' font-weight='bold' font-family='IBM Plex Sans' fill='#FFFFFF' fill-opacity='1'>Harris<\\/text>\\n   <text x='150.47' y='188.74' font-size='10.67pt' font-weight='bold' font-family='IBM Plex Sans' fill='#FFFFFF' fill-opacity='1'>49.4%<\\/text>\\n   <text x='152.49' y='168.68' font-size='10.67pt' font-weight='bold' font-family='IBM Plex Sans' fill='#FFFFFF' fill-opacity='1'>Harris<\\/text>\\n   <text x='151.12' y='189.17' font-size='10.67pt' font-weight='bold' font-family='IBM Plex Sans' fill='#FFFFFF' fill-opacity='1'>49.4%<\\/text>\\n   <text x='153.25' y='168.83' font-size='10.67pt' font-weight='bold' font-family='IBM Plex Sans' fill='#FFFFFF' fill-opacity='1'>Harris<\\/text>\\n   <text x='151.88' y='189.32' font-size='10.67pt' font-weight='bold' font-family='IBM Plex Sans' fill='#FFFFFF' fill-opacity='1'>49.4%<\\/text>\\n   <text x='154.01' y='168.68' font-size='10.67pt' font-weight='bold' font-family='IBM Plex Sans' fill='#FFFFFF' fill-opacity='1'>Harris<\\/text>\\n   <text x='152.64' y='189.17' font-size='10.67pt' font-weight='bold' font-family='IBM Plex Sans' fill='#FFFFFF' fill-opacity='1'>49.4%<\\/text>\\n   <text x='154.65' y='168.25' font-size='10.67pt' font-weight='bold' font-family='IBM Plex Sans' fill='#FFFFFF' fill-opacity='1'>Harris<\\/text>\\n   <text x='153.28' y='188.74' font-size='10.67pt' font-weight='bold' font-family='IBM Plex Sans' fill='#FFFFFF' fill-opacity='1'>49.4%<\\/text>\\n   <text x='155.08' y='167.61' font-size='10.67pt' font-weight='bold' font-family='IBM Plex Sans' fill='#FFFFFF' fill-opacity='1'>Harris<\\/text>\\n   <text x='153.71' y='188.09' font-size='10.67pt' font-weight='bold' font-family='IBM Plex Sans' fill='#FFFFFF' fill-opacity='1'>49.4%<\\/text>\\n   <text x='155.23' y='166.85' font-size='10.67pt' font-weight='bold' font-family='IBM Plex Sans' fill='#FFFFFF' fill-opacity='1'>Harris<\\/text>\\n   <text x='153.86' y='187.33' font-size='10.67pt' font-weight='bold' font-family='IBM Plex Sans' fill='#FFFFFF' fill-opacity='1'>49.4%<\\/text>\\n   <text x='153.25' y='166.85' font-size='10.67pt' font-weight='bold' font-family='IBM Plex Sans' fill='#3579AC' fill-opacity='1'>Harris<\\/text>\\n   <text x='151.88' y='187.33' font-size='10.67pt' font-weight='bold' font-family='IBM Plex Sans' fill='#3579AC' fill-opacity='1'>49.4%<\\/text>\\n   <rect id='svg_1c198605_0a6c_4f9e_8e95_555ee0d0f554_e1' x='91.33' y='36.7' width='7.17' height='232.78' fill='#333333' fill-opacity='0' stroke='none' title='August 1st&amp;lt;br&amp;gt;Harris: &amp;lt;span style=&amp;#39;float:right;&amp;#39;&amp;gt;49.1%&amp;lt;/span&amp;gt;&amp;lt;br&amp;gt;Trump: &amp;lt;span style=&amp;#39;float:right;&amp;#39;&amp;gt;50.9%&amp;lt;/span&amp;gt;'/>\\n   <rect id='svg_1c198605_0a6c_4f9e_8e95_555ee0d0f554_e2' x='98.5' y='36.7' width='7.17' height='232.78' fill='#333333' fill-opacity='0' stroke='none' title='August 2nd&amp;lt;br&amp;gt;Harris: &amp;lt;span style=&amp;#39;float:right;&amp;#39;&amp;gt;49.0%&amp;lt;/span&amp;gt;&amp;lt;br&amp;gt;Trump: &amp;lt;span style=&amp;#39;float:right;&amp;#39;&amp;gt;51.0%&amp;lt;/span&amp;gt;'/>\\n   <rect id='svg_1c198605_0a6c_4f9e_8e95_555ee0d0f554_e3' x='105.67' y='36.7' width='7.17' height='232.78' fill='#333333' fill-opacity='0' stroke='none' title='August 3rd&amp;lt;br&amp;gt;Harris: &amp;lt;span style=&amp;#39;float:right;&amp;#39;&amp;gt;49.2%&amp;lt;/span&amp;gt;&amp;lt;br&amp;gt;Trump: &amp;lt;span style=&amp;#39;float:right;&amp;#39;&amp;gt;50.8%&amp;lt;/span&amp;gt;'/>\\n   <rect id='svg_1c198605_0a6c_4f9e_8e95_555ee0d0f554_e4' x='112.84' y='36.7' width='7.17' height='232.78' fill='#333333' fill-opacity='0' stroke='none' title='August 4th&amp;lt;br&amp;gt;Harris: &amp;lt;span style=&amp;#39;float:right;&amp;#39;&amp;gt;49.2%&amp;lt;/span&amp;gt;&amp;lt;br&amp;gt;Trump: &amp;lt;span style=&amp;#39;float:right;&amp;#39;&amp;gt;50.8%&amp;lt;/span&amp;gt;'/>\\n   <rect id='svg_1c198605_0a6c_4f9e_8e95_555ee0d0f554_e5' x='120.01' y='36.7' width='7.17' height='232.78' fill='#333333' fill-opacity='0' stroke='none' title='August 5th&amp;lt;br&amp;gt;Harris: &amp;lt;span style=&amp;#39;float:right;&amp;#39;&amp;gt;49.3%&amp;lt;/span&amp;gt;&amp;lt;br&amp;gt;Trump: &amp;lt;span style=&amp;#39;float:right;&amp;#39;&amp;gt;50.7%&amp;lt;/span&amp;gt;'/>\\n   <rect id='svg_1c198605_0a6c_4f9e_8e95_555ee0d0f554_e6' x='127.19' y='36.7' width='7.17' height='232.78' fill='#333333' fill-opacity='0' stroke='none' title='August 6th&amp;lt;br&amp;gt;Harris: &amp;lt;span style=&amp;#39;float:right;&amp;#39;&amp;gt;49.4%&amp;lt;/span&amp;gt;&amp;lt;br&amp;gt;Trump: &amp;lt;span style=&amp;#39;float:right;&amp;#39;&amp;gt;50.6%&amp;lt;/span&amp;gt;'/>\\n   <rect id='svg_1c198605_0a6c_4f9e_8e95_555ee0d0f554_e7' x='134.36' y='36.7' width='7.17' height='232.78' fill='#333333' fill-opacity='0' stroke='none' title='August 7th&amp;lt;br&amp;gt;Harris: &amp;lt;span style=&amp;#39;float:right;&amp;#39;&amp;gt;49.4%&amp;lt;/span&amp;gt;&amp;lt;br&amp;gt;Trump: &amp;lt;span style=&amp;#39;float:right;&amp;#39;&amp;gt;50.6%&amp;lt;/span&amp;gt;'/>\\n  <\\/g>\\n <\\/g>\\n<\\/svg>\",\"js\":null,\"uid\":\"svg_1c198605_0a6c_4f9e_8e95_555ee0d0f554\",\"ratio\":3,\"settings\":{\"tooltip\":{\"css\":\".tooltip_SVGID_ { font-family:IBM Plex Sans;color:#363a3c;background-color:#fafafa;padding:5px;border-radius:3px;border-color:black;border-style:solid;border-width:0.125em 0em 0em 0em;box-shadow: 0px 0px 10px 5px lightgray;min-width: 120px ; position:absolute;pointer-events:none;z-index:999;}\",\"placement\":\"doc\",\"opacity\":1,\"offx\":10,\"offy\":0,\"use_cursor_pos\":true,\"use_fill\":false,\"use_stroke\":false,\"delay_over\":200,\"delay_out\":500},\"hover\":{\"css\":\".hover_data_SVGID_ { fill:orange;stroke:black;cursor:pointer; }\\ntext.hover_data_SVGID_ { stroke:none;fill:orange; }\\ncircle.hover_data_SVGID_ { fill:orange;stroke:black; }\\nline.hover_data_SVGID_, polyline.hover_data_SVGID_ { fill:none;stroke:orange; }\\nrect.hover_data_SVGID_, polygon.hover_data_SVGID_, path.hover_data_SVGID_ { fill:orange;stroke:none; }\\nimage.hover_data_SVGID_ { stroke:orange; }\",\"reactive\":true,\"nearest_distance\":null},\"hover_inv\":{\"css\":\"\"},\"hover_key\":{\"css\":\".hover_key_SVGID_ { fill:orange;stroke:black;cursor:pointer; }\\ntext.hover_key_SVGID_ { stroke:none;fill:orange; }\\ncircle.hover_key_SVGID_ { fill:orange;stroke:black; }\\nline.hover_key_SVGID_, polyline.hover_key_SVGID_ { fill:none;stroke:orange; }\\nrect.hover_key_SVGID_, polygon.hover_key_SVGID_, path.hover_key_SVGID_ { fill:orange;stroke:none; }\\nimage.hover_key_SVGID_ { stroke:orange; }\",\"reactive\":true},\"hover_theme\":{\"css\":\".hover_theme_SVGID_ { fill:orange;stroke:black;cursor:pointer; }\\ntext.hover_theme_SVGID_ { stroke:none;fill:orange; }\\ncircle.hover_theme_SVGID_ { fill:orange;stroke:black; }\\nline.hover_theme_SVGID_, polyline.hover_theme_SVGID_ { fill:none;stroke:orange; }\\nrect.hover_theme_SVGID_, polygon.hover_theme_SVGID_, path.hover_theme_SVGID_ { fill:orange;stroke:none; }\\nimage.hover_theme_SVGID_ { stroke:orange; }\",\"reactive\":true},\"select\":{\"css\":\".select_data_SVGID_ { fill:red;stroke:black;cursor:pointer; }\\ntext.select_data_SVGID_ { stroke:none;fill:red; }\\ncircle.select_data_SVGID_ { fill:red;stroke:black; }\\nline.select_data_SVGID_, polyline.select_data_SVGID_ { fill:none;stroke:red; }\\nrect.select_data_SVGID_, polygon.select_data_SVGID_, path.select_data_SVGID_ { fill:red;stroke:none; }\\nimage.select_data_SVGID_ { stroke:red; }\",\"type\":\"multiple\",\"only_shiny\":true,\"selected\":[]},\"select_inv\":{\"css\":\"\"},\"select_key\":{\"css\":\".select_key_SVGID_ { fill:red;stroke:black;cursor:pointer; }\\ntext.select_key_SVGID_ { stroke:none;fill:red; }\\ncircle.select_key_SVGID_ { fill:red;stroke:black; }\\nline.select_key_SVGID_, polyline.select_key_SVGID_ { fill:none;stroke:red; }\\nrect.select_key_SVGID_, polygon.select_key_SVGID_, path.select_key_SVGID_ { fill:red;stroke:none; }\\nimage.select_key_SVGID_ { stroke:red; }\",\"type\":\"single\",\"only_shiny\":true,\"selected\":[]},\"select_theme\":{\"css\":\".select_theme_SVGID_ { fill:red;stroke:black;cursor:pointer; }\\ntext.select_theme_SVGID_ { stroke:none;fill:red; }\\ncircle.select_theme_SVGID_ { fill:red;stroke:black; }\\nline.select_theme_SVGID_, polyline.select_theme_SVGID_ { fill:none;stroke:red; }\\nrect.select_theme_SVGID_, polygon.select_theme_SVGID_, path.select_theme_SVGID_ { fill:red;stroke:none; }\\nimage.select_theme_SVGID_ { stroke:red; }\",\"type\":\"single\",\"only_shiny\":true,\"selected\":[]},\"zoom\":{\"min\":1,\"max\":1,\"duration\":300},\"toolbar\":{\"position\":\"topright\",\"pngname\":\"diagram\",\"tooltips\":null,\"fixed\":false,\"hidden\":[],\"delay_over\":200,\"delay_out\":500},\"sizing\":{\"rescale\":true,\"width\":1}}},\"evals\":[],\"jsHooks\":[]}</script>\n```\n\n:::\n:::\n\n<br><span style='display:inline-block;width:60%;'>*No polls have been conducted in Nebraska CD-2. The projected voteshare is estimated using economic and approval indicators, as well as polling information from similar states.*</span><br>\n\n::: {.cell}\n\n:::\n\n\n\n---\n\n:::: {.columns}\n::: {.column width=\"60%\"}\n\n\n### <span style='font-family:Playfair Display;'>State similarities</span>\nThe model uses state characteristics, like demographic composition, population density, and education, to estimate how similar states are to one another.\nSimilar states are more likely to share polling biases and see similar shifts in polling trendlines.\n\n\n:::\n::: {.column width=\"40%\"}\n:::\n::::\n\n\n\n![](https://raw.githubusercontent.com/markjrieke/2024-potus/main/img/Nebraska CD-2.png){height=700 fig-align='center'}\n\n\n\n---\n\n:::: {.columns}\n::: {.column width=\"30%\"}\n\n\n<span style='color:gray;font-size:12px'>\nSources: Ballotpedia; Cook Political Report; The Economist; Federal Reserve Bank of St. Louis; FiveThirtyEight; Urban Stats; 270towin.com\n<br>\n<br>\n[{{< fa brands github >}} View the source code](https://github.com/markjrieke/2024-potus/tree/main)\n<br>\n[{{< fa solid database >}} Explore the output](https://github.com/markjrieke/2024-potus/tree/main/out)\n</span>\n\n\n:::\n::::\n\n---\n\n:::::\n\n::::: {.column-margin-custom}\n\n\n\n**[National Forecast](National.qmd)**<br>[How this works](../posts/2024-07-04-forecast-methodology/index.qmd)\n\n<br>**Competitive states**<br>[Nebraska CD-2](Nebraska CD-2.qmd)<br>[Michigan](Michigan.qmd)<br>[Wisconsin](Wisconsin.qmd)<br>[Pennsylvania](Pennsylvania.qmd)<br>[New Hampshire](New Hampshire.qmd)<br>[Minnesota](Minnesota.qmd)<br>[Nevada](Nevada.qmd)<br>[Virginia](Virginia.qmd)<br>[Maine](Maine.qmd)<br>[Georgia](Georgia.qmd)<br>[New Mexico](New Mexico.qmd)<br>[Arizona](Arizona.qmd)<br>[North Carolina](North Carolina.qmd)<br>[Colorado](Colorado.qmd)<br>[Oregon](Oregon.qmd)\n\n<br>**All states**<br>[Alabama](Alabama.qmd)<br>[Alaska](Alaska.qmd)<br>[Arizona](Arizona.qmd)<br>[Arkansas](Arkansas.qmd)<br>[California](California.qmd)<br>[Colorado](Colorado.qmd)<br>[Connecticut](Connecticut.qmd)<br>[Delaware](Delaware.qmd)<br>[District of Columbia](District of Columbia.qmd)<br>[Florida](Florida.qmd)<br>[Georgia](Georgia.qmd)<br>[Hawaii](Hawaii.qmd)<br>[Idaho](Idaho.qmd)<br>[Illinois](Illinois.qmd)<br>[Indiana](Indiana.qmd)<br>[Iowa](Iowa.qmd)<br>[Kansas](Kansas.qmd)<br>[Kentucky](Kentucky.qmd)<br>[Louisiana](Louisiana.qmd)<br>[Maine CD-1](Maine CD-1.qmd)<br>[Maine CD-2](Maine CD-2.qmd)<br>[Maine](Maine.qmd)<br>[Maryland](Maryland.qmd)<br>[Massachusetts](Massachusetts.qmd)<br>[Michigan](Michigan.qmd)<br>[Minnesota](Minnesota.qmd)<br>[Mississippi](Mississippi.qmd)<br>[Missouri](Missouri.qmd)<br>[Montana](Montana.qmd)<br>[Nebraska CD-1](Nebraska CD-1.qmd)<br>[Nebraska CD-2](Nebraska CD-2.qmd)<br>[Nebraska CD-3](Nebraska CD-3.qmd)<br>[Nebraska](Nebraska.qmd)<br>[Nevada](Nevada.qmd)<br>[New Hampshire](New Hampshire.qmd)<br>[New Jersey](New Jersey.qmd)<br>[New Mexico](New Mexico.qmd)<br>[New York](New York.qmd)<br>[North Carolina](North Carolina.qmd)<br>[North Dakota](North Dakota.qmd)<br>[Ohio](Ohio.qmd)<br>[Oklahoma](Oklahoma.qmd)<br>[Oregon](Oregon.qmd)<br>[Pennsylvania](Pennsylvania.qmd)<br>[Rhode Island](Rhode Island.qmd)<br>[South Carolina](South Carolina.qmd)<br>[South Dakota](South Dakota.qmd)<br>[Tennessee](Tennessee.qmd)<br>[Texas](Texas.qmd)<br>[Utah](Utah.qmd)<br>[Vermont](Vermont.qmd)<br>[Virginia](Virginia.qmd)<br>[Washington](Washington.qmd)<br>[West Virginia](West Virginia.qmd)<br>[Wisconsin](Wisconsin.qmd)<br>[Wyoming](Wyoming.qmd)\n\n\n\n:::::\n\n",
    "supporting": [],
    "filters": [
      "rmarkdown/pagebreak.lua"
    ],
    "includes": {
      "include-in-header": [
        "<link href=\"../site_libs/htmltools-fill-0.5.8.1/fill.css\" rel=\"stylesheet\" />\n<script src=\"../site_libs/htmlwidgets-1.6.4/htmlwidgets.js\"></script>\n<script src=\"../site_libs/d3-bundle-5.16.0/d3-bundle.min.js\"></script>\n<script src=\"../site_libs/d3-lasso-0.0.5/d3-lasso.min.js\"></script>\n<script src=\"../site_libs/save-svg-as-png-1.4.17/save-svg-as-png.min.js\"></script>\n<script src=\"../site_libs/flatbush-4.4.0/flatbush.min.js\"></script>\n<link href=\"../site_libs/ggiraphjs-0.8.10/ggiraphjs.min.css\" rel=\"stylesheet\" />\n<script src=\"../site_libs/ggiraphjs-0.8.10/ggiraphjs.min.js\"></script>\n<script src=\"../site_libs/girafe-binding-0.8.10/girafe.js\"></script>\n"
      ]
    },
    "engineDependencies": {},
    "preserve": {},
    "postProcess": true
  }
}