{
  "hash": "33ef22863f8e8a8325bc405c8322e46f",
  "result": {
    "engine": "knitr",
    "markdown": "---\nformat: \n  html:\n    code-fold: true\n    page-layout: custom\n    fig-align: center\n    fig-width: 12\n    fig-height: 4\nexecute: \n  message: false\n  warning: false\n  echo: false\nparams:\n  state: \"Oklahoma\"\n  branch: \"dev\"\n---\n\n::: {.cell}\n\n:::\n\n\n\n::::: {.column-body-custom}\n\n:::: {.columns}\n::: {.column width=\"80%\"}\n\n\n<span style='font-family:Playfair Display;font-size:36px;'>As of August 22nd, the forecast indicates that **Kamala Harris is likely to beat Donald Trump** in Colorado.</span>\n\n\n:::\n::: {.column width=\"20%\"}\n:::\n::::\n\n---\n\n:::: {.columns}\n::: {.column width=\"60%\"}\n\n\n### <span style='font-family:Playfair Display;'>Presidential probabilities</span>\nEach day, the model simulates thousands of plausible election results, from landslide victories to tightly contested races.\nEach candidate’s probability of winning is the proportion of simulations that they’ve won.\n\n\n:::\n::: {.column width=\"40%\"}\n:::\n::::\n\n\n\n::: {.cell}\n::: {.cell-output-display}\n\n```{=html}\n<div class=\"girafe html-widget html-fill-item\" id=\"htmlwidget-ac5bced8217666132da4\" style=\"width:100%;height:216px;\"></div>\n<script type=\"application/json\" data-for=\"htmlwidget-ac5bced8217666132da4\">{\"x\":{\"html\":\"<?xml version=\\\"1.0\\\" encoding=\\\"UTF-8\\\"?>\\n<svg xmlns='http://www.w3.org/2000/svg' xmlns:xlink='http://www.w3.org/1999/xlink' class='ggiraph-svg' role='graphics-document' id='svg_171e6422_7ffe_43c2_b5d0_9cbaf74be05d' viewBox='0 0 864 288'>\\n <defs id='svg_171e6422_7ffe_43c2_b5d0_9cbaf74be05d_defs'>\\n  <clipPath id='svg_171e6422_7ffe_43c2_b5d0_9cbaf74be05d_c1'>\\n   <rect x='0' y='0' width='864' height='288'/>\\n  <\\/clipPath>\\n  <clipPath id='svg_171e6422_7ffe_43c2_b5d0_9cbaf74be05d_c2'>\\n   <rect x='5.98' y='5.98' width='852.04' height='276.04'/>\\n  <\\/clipPath>\\n <\\/defs>\\n <g id='svg_171e6422_7ffe_43c2_b5d0_9cbaf74be05d_rootg' class='ggiraph-svg-rootg'>\\n  <g clip-path='url(#svg_171e6422_7ffe_43c2_b5d0_9cbaf74be05d_c1)'>\\n   <rect x='0' y='0' width='864' height='288' fill='#FFFFFF' fill-opacity='1' stroke='#FFFFFF' stroke-opacity='1' stroke-width='0.75' stroke-linejoin='round' stroke-linecap='round' class='ggiraph-svg-bg'/>\\n   <rect x='0' y='0' width='864' height='288' fill='#FFFFFF' fill-opacity='1' stroke='#FFFFFF' stroke-opacity='1' stroke-width='1.16' stroke-linejoin='round' stroke-linecap='round'/>\\n  <\\/g>\\n  <g clip-path='url(#svg_171e6422_7ffe_43c2_b5d0_9cbaf74be05d_c2)'>\\n   <polyline points='5.98,269.47 858.02,269.47' fill='none' stroke='#EBEBEB' stroke-opacity='1' stroke-width='0.53' stroke-linejoin='round' stroke-linecap='butt'/>\\n   <polyline points='5.98,211.28 858.02,211.28' fill='none' stroke='#EBEBEB' stroke-opacity='1' stroke-width='0.53' stroke-linejoin='round' stroke-linecap='butt'/>\\n   <polyline points='5.98,153.09 858.02,153.09' fill='none' stroke='#EBEBEB' stroke-opacity='1' stroke-width='0.53' stroke-linejoin='round' stroke-linecap='butt'/>\\n   <polyline points='5.98,94.89 858.02,94.89' fill='none' stroke='#EBEBEB' stroke-opacity='1' stroke-width='0.53' stroke-linejoin='round' stroke-linecap='butt'/>\\n   <polyline points='5.98,36.70 858.02,36.70' fill='none' stroke='#EBEBEB' stroke-opacity='1' stroke-width='0.53' stroke-linejoin='round' stroke-linecap='butt'/>\\n  <\\/g>\\n  <g clip-path='url(#svg_171e6422_7ffe_43c2_b5d0_9cbaf74be05d_c1)'>\\n   <polyline points='94.91,272.46 94.91,269.47' fill='none' stroke='#000000' stroke-opacity='1' stroke-width='1.16' stroke-linejoin='round' stroke-linecap='butt'/>\\n   <polyline points='317.25,272.46 317.25,269.47' fill='none' stroke='#000000' stroke-opacity='1' stroke-width='1.16' stroke-linejoin='round' stroke-linecap='butt'/>\\n   <polyline points='532.41,272.46 532.41,269.47' fill='none' stroke='#000000' stroke-opacity='1' stroke-width='1.16' stroke-linejoin='round' stroke-linecap='butt'/>\\n   <polyline points='754.74,272.46 754.74,269.47' fill='none' stroke='#000000' stroke-opacity='1' stroke-width='1.16' stroke-linejoin='round' stroke-linecap='butt'/>\\n   <text x='79.83' y='281.55' font-size='7.2pt' font-family='IBM Plex Sans' fill='#363A3C' fill-opacity='1'>August<\\/text>\\n   <text x='293.37' y='281.55' font-size='7.2pt' font-family='IBM Plex Sans' fill='#363A3C' fill-opacity='1'>September<\\/text>\\n   <text x='515.06' y='281.55' font-size='7.2pt' font-family='IBM Plex Sans' fill='#363A3C' fill-opacity='1'>October<\\/text>\\n   <text x='732.32' y='281.55' font-size='7.2pt' font-family='IBM Plex Sans' fill='#363A3C' fill-opacity='1'>November<\\/text>\\n   <text x='11.36' y='263.08' font-size='7.2pt' font-family='IBM Plex Sans' fill='#363A3C' fill-opacity='1'>0%<\\/text>\\n   <text x='11.36' y='204.89' font-size='7.2pt' font-family='IBM Plex Sans' fill='#363A3C' fill-opacity='1'>25%<\\/text>\\n   <text x='11.36' y='146.69' font-size='7.2pt' font-family='IBM Plex Sans' fill='#363A3C' fill-opacity='1'>50%<\\/text>\\n   <text x='11.36' y='88.5' font-size='7.2pt' font-family='IBM Plex Sans' fill='#363A3C' fill-opacity='1'>75%<\\/text>\\n   <text x='11.36' y='30.3' font-size='7.2pt' font-family='IBM Plex Sans' fill='#363A3C' fill-opacity='1'>100%<\\/text>\\n  <\\/g>\\n  <g clip-path='url(#svg_171e6422_7ffe_43c2_b5d0_9cbaf74be05d_c2)'>\\n   <line x1='5.98' y1='269.47' x2='858.02' y2='269.47' stroke='#363A3C' stroke-opacity='1' stroke-width='0.64' stroke-linejoin='round' stroke-linecap='butt'/>\\n   <line x1='5.98' y1='153.09' x2='858.02' y2='153.09' stroke='#363A3C' stroke-opacity='1' stroke-width='0.64' stroke-linejoin='round' stroke-linecap='butt'/>\\n   <line x1='783.43' y1='269.47' x2='783.43' y2='27.18' stroke='#333333' stroke-opacity='1' stroke-width='0.85' stroke-linejoin='round' stroke-linecap='butt'/>\\n   <polygon points='783.43,30.22 786.07,25.66 780.80,25.66' fill='#333333' fill-opacity='1' stroke='#333333' stroke-opacity='1' stroke-width='0.71' stroke-linejoin='round' stroke-linecap='round'/>\\n   <text x='755.69' y='22' font-size='7.47pt' font-family='IBM Plex Sans' fill='#333333' fill-opacity='1'>Election Day<\\/text>\\n   <line x1='245.53' y1='269.47' x2='245.53' y2='36.7' stroke='#333333' stroke-opacity='1' stroke-width='0.85' stroke-linejoin='round' stroke-linecap='butt'/>\\n   <polygon points='245.53,39.74 248.16,35.18 242.89,35.18' fill='#333333' fill-opacity='1' stroke='#333333' stroke-opacity='1' stroke-width='0.71' stroke-linejoin='round' stroke-linecap='round'/>\\n   <text x='218.96' y='29.85' font-size='7.47pt' font-family='IBM Plex Sans' fill='#FFFFFF' fill-opacity='1'>August 22nd<\\/text>\\n   <text x='218.51' y='29.18' font-size='7.47pt' font-family='IBM Plex Sans' fill='#FFFFFF' fill-opacity='1'>August 22nd<\\/text>\\n   <text x='217.83' y='28.73' font-size='7.47pt' font-family='IBM Plex Sans' fill='#FFFFFF' fill-opacity='1'>August 22nd<\\/text>\\n   <text x='217.03' y='28.57' font-size='7.47pt' font-family='IBM Plex Sans' fill='#FFFFFF' fill-opacity='1'>August 22nd<\\/text>\\n   <text x='216.23' y='28.73' font-size='7.47pt' font-family='IBM Plex Sans' fill='#FFFFFF' fill-opacity='1'>August 22nd<\\/text>\\n   <text x='215.56' y='29.18' font-size='7.47pt' font-family='IBM Plex Sans' fill='#FFFFFF' fill-opacity='1'>August 22nd<\\/text>\\n   <text x='215.11' y='29.85' font-size='7.47pt' font-family='IBM Plex Sans' fill='#FFFFFF' fill-opacity='1'>August 22nd<\\/text>\\n   <text x='214.95' y='30.65' font-size='7.47pt' font-family='IBM Plex Sans' fill='#FFFFFF' fill-opacity='1'>August 22nd<\\/text>\\n   <text x='215.11' y='31.45' font-size='7.47pt' font-family='IBM Plex Sans' fill='#FFFFFF' fill-opacity='1'>August 22nd<\\/text>\\n   <text x='215.56' y='32.13' font-size='7.47pt' font-family='IBM Plex Sans' fill='#FFFFFF' fill-opacity='1'>August 22nd<\\/text>\\n   <text x='216.23' y='32.58' font-size='7.47pt' font-family='IBM Plex Sans' fill='#FFFFFF' fill-opacity='1'>August 22nd<\\/text>\\n   <text x='217.03' y='32.74' font-size='7.47pt' font-family='IBM Plex Sans' fill='#FFFFFF' fill-opacity='1'>August 22nd<\\/text>\\n   <text x='217.83' y='32.58' font-size='7.47pt' font-family='IBM Plex Sans' fill='#FFFFFF' fill-opacity='1'>August 22nd<\\/text>\\n   <text x='218.51' y='32.13' font-size='7.47pt' font-family='IBM Plex Sans' fill='#FFFFFF' fill-opacity='1'>August 22nd<\\/text>\\n   <text x='218.96' y='31.45' font-size='7.47pt' font-family='IBM Plex Sans' fill='#FFFFFF' fill-opacity='1'>August 22nd<\\/text>\\n   <text x='219.12' y='30.65' font-size='7.47pt' font-family='IBM Plex Sans' fill='#FFFFFF' fill-opacity='1'>August 22nd<\\/text>\\n   <text x='217.03' y='30.65' font-size='7.47pt' font-family='IBM Plex Sans' fill='#333333' fill-opacity='1'>August 22nd<\\/text>\\n   <polyline points='94.91,211.16 102.08,210.02 109.26,209.95 116.43,215.14 123.60,214.24 130.77,216.66 137.94,217.19 145.12,217.66 152.29,218.33 159.46,217.91 166.63,218.22 173.80,220.13 180.98,221.45 188.15,219.80 195.32,219.45 202.49,221.50 209.67,218.12 216.84,218.64 224.01,218.38 231.18,222.87 238.35,221.50 245.53,224.34' fill='none' stroke='#FFFFFF' stroke-opacity='1' stroke-width='5.33' stroke-linejoin='round' stroke-linecap='butt'/>\\n   <polyline points='94.91,211.16 102.08,210.02 109.26,209.95 116.43,215.14 123.60,214.24 130.77,216.66 137.94,217.19 145.12,217.66 152.29,218.33 159.46,217.91 166.63,218.22 173.80,220.13 180.98,221.45 188.15,219.80 195.32,219.45 202.49,221.50 209.67,218.12 216.84,218.64 224.01,218.38 231.18,222.87 238.35,221.50 245.53,224.34' fill='none' stroke='#B13737' stroke-opacity='1' stroke-width='1.71' stroke-linejoin='round' stroke-linecap='butt'/>\\n   <polyline points='94.91,95.01 102.08,96.15 109.26,96.22 116.43,91.03 123.60,91.94 130.77,89.51 137.94,88.98 145.12,88.51 152.29,87.84 159.46,88.26 166.63,87.95 173.80,86.05 180.98,84.72 188.15,86.37 195.32,86.72 202.49,84.67 209.67,88.05 216.84,87.54 224.01,87.79 231.18,83.30 238.35,84.67 245.53,81.83' fill='none' stroke='#FFFFFF' stroke-opacity='1' stroke-width='5.33' stroke-linejoin='round' stroke-linecap='butt'/>\\n   <polyline points='94.91,95.01 102.08,96.15 109.26,96.22 116.43,91.03 123.60,91.94 130.77,89.51 137.94,88.98 145.12,88.51 152.29,87.84 159.46,88.26 166.63,87.95 173.80,86.05 180.98,84.72 188.15,86.37 195.32,86.72 202.49,84.67 209.67,88.05 216.84,87.54 224.01,87.79 231.18,83.30 238.35,84.67 245.53,81.83' fill='none' stroke='#3579AC' stroke-opacity='1' stroke-width='1.71' stroke-linejoin='round' stroke-linecap='butt'/>\\n   <circle cx='245.53' cy='224.34' r='2.27pt' fill='#B13737' fill-opacity='1' stroke='#B13737' stroke-opacity='1' stroke-width='0.71' stroke-linejoin='round' stroke-linecap='round'/>\\n   <circle cx='245.53' cy='81.83' r='2.27pt' fill='#3579AC' fill-opacity='1' stroke='#3579AC' stroke-opacity='1' stroke-width='0.71' stroke-linejoin='round' stroke-linecap='round'/>\\n   <text x='261.28' y='218.3' font-size='10.67pt' font-weight='bold' font-family='IBM Plex Sans' fill='#FFFFFF' fill-opacity='1'>Trump<\\/text>\\n   <text x='267.76' y='238.79' font-size='10.67pt' font-weight='bold' font-family='IBM Plex Sans' fill='#FFFFFF' fill-opacity='1'>19%<\\/text>\\n   <text x='260.85' y='217.66' font-size='10.67pt' font-weight='bold' font-family='IBM Plex Sans' fill='#FFFFFF' fill-opacity='1'>Trump<\\/text>\\n   <text x='267.33' y='238.14' font-size='10.67pt' font-weight='bold' font-family='IBM Plex Sans' fill='#FFFFFF' fill-opacity='1'>19%<\\/text>\\n   <text x='260.2' y='217.23' font-size='10.67pt' font-weight='bold' font-family='IBM Plex Sans' fill='#FFFFFF' fill-opacity='1'>Trump<\\/text>\\n   <text x='266.69' y='237.71' font-size='10.67pt' font-weight='bold' font-family='IBM Plex Sans' fill='#FFFFFF' fill-opacity='1'>19%<\\/text>\\n   <text x='259.44' y='217.07' font-size='10.67pt' font-weight='bold' font-family='IBM Plex Sans' fill='#FFFFFF' fill-opacity='1'>Trump<\\/text>\\n   <text x='265.93' y='237.56' font-size='10.67pt' font-weight='bold' font-family='IBM Plex Sans' fill='#FFFFFF' fill-opacity='1'>19%<\\/text>\\n   <text x='258.68' y='217.23' font-size='10.67pt' font-weight='bold' font-family='IBM Plex Sans' fill='#FFFFFF' fill-opacity='1'>Trump<\\/text>\\n   <text x='265.17' y='237.71' font-size='10.67pt' font-weight='bold' font-family='IBM Plex Sans' fill='#FFFFFF' fill-opacity='1'>19%<\\/text>\\n   <text x='258.04' y='217.66' font-size='10.67pt' font-weight='bold' font-family='IBM Plex Sans' fill='#FFFFFF' fill-opacity='1'>Trump<\\/text>\\n   <text x='264.52' y='238.14' font-size='10.67pt' font-weight='bold' font-family='IBM Plex Sans' fill='#FFFFFF' fill-opacity='1'>19%<\\/text>\\n   <text x='257.61' y='218.3' font-size='10.67pt' font-weight='bold' font-family='IBM Plex Sans' fill='#FFFFFF' fill-opacity='1'>Trump<\\/text>\\n   <text x='264.09' y='238.79' font-size='10.67pt' font-weight='bold' font-family='IBM Plex Sans' fill='#FFFFFF' fill-opacity='1'>19%<\\/text>\\n   <text x='257.46' y='219.06' font-size='10.67pt' font-weight='bold' font-family='IBM Plex Sans' fill='#FFFFFF' fill-opacity='1'>Trump<\\/text>\\n   <text x='263.94' y='239.55' font-size='10.67pt' font-weight='bold' font-family='IBM Plex Sans' fill='#FFFFFF' fill-opacity='1'>19%<\\/text>\\n   <text x='257.61' y='219.82' font-size='10.67pt' font-weight='bold' font-family='IBM Plex Sans' fill='#FFFFFF' fill-opacity='1'>Trump<\\/text>\\n   <text x='264.09' y='240.31' font-size='10.67pt' font-weight='bold' font-family='IBM Plex Sans' fill='#FFFFFF' fill-opacity='1'>19%<\\/text>\\n   <text x='258.04' y='220.46' font-size='10.67pt' font-weight='bold' font-family='IBM Plex Sans' fill='#FFFFFF' fill-opacity='1'>Trump<\\/text>\\n   <text x='264.52' y='240.95' font-size='10.67pt' font-weight='bold' font-family='IBM Plex Sans' fill='#FFFFFF' fill-opacity='1'>19%<\\/text>\\n   <text x='258.68' y='220.9' font-size='10.67pt' font-weight='bold' font-family='IBM Plex Sans' fill='#FFFFFF' fill-opacity='1'>Trump<\\/text>\\n   <text x='265.17' y='241.38' font-size='10.67pt' font-weight='bold' font-family='IBM Plex Sans' fill='#FFFFFF' fill-opacity='1'>19%<\\/text>\\n   <text x='259.44' y='221.05' font-size='10.67pt' font-weight='bold' font-family='IBM Plex Sans' fill='#FFFFFF' fill-opacity='1'>Trump<\\/text>\\n   <text x='265.93' y='241.53' font-size='10.67pt' font-weight='bold' font-family='IBM Plex Sans' fill='#FFFFFF' fill-opacity='1'>19%<\\/text>\\n   <text x='260.2' y='220.9' font-size='10.67pt' font-weight='bold' font-family='IBM Plex Sans' fill='#FFFFFF' fill-opacity='1'>Trump<\\/text>\\n   <text x='266.69' y='241.38' font-size='10.67pt' font-weight='bold' font-family='IBM Plex Sans' fill='#FFFFFF' fill-opacity='1'>19%<\\/text>\\n   <text x='260.85' y='220.46' font-size='10.67pt' font-weight='bold' font-family='IBM Plex Sans' fill='#FFFFFF' fill-opacity='1'>Trump<\\/text>\\n   <text x='267.33' y='240.95' font-size='10.67pt' font-weight='bold' font-family='IBM Plex Sans' fill='#FFFFFF' fill-opacity='1'>19%<\\/text>\\n   <text x='261.28' y='219.82' font-size='10.67pt' font-weight='bold' font-family='IBM Plex Sans' fill='#FFFFFF' fill-opacity='1'>Trump<\\/text>\\n   <text x='267.76' y='240.31' font-size='10.67pt' font-weight='bold' font-family='IBM Plex Sans' fill='#FFFFFF' fill-opacity='1'>19%<\\/text>\\n   <text x='261.43' y='219.06' font-size='10.67pt' font-weight='bold' font-family='IBM Plex Sans' fill='#FFFFFF' fill-opacity='1'>Trump<\\/text>\\n   <text x='267.91' y='239.55' font-size='10.67pt' font-weight='bold' font-family='IBM Plex Sans' fill='#FFFFFF' fill-opacity='1'>19%<\\/text>\\n   <text x='259.44' y='219.06' font-size='10.67pt' font-weight='bold' font-family='IBM Plex Sans' fill='#B13737' fill-opacity='1'>Trump<\\/text>\\n   <text x='265.93' y='239.55' font-size='10.67pt' font-weight='bold' font-family='IBM Plex Sans' fill='#B13737' fill-opacity='1'>19%<\\/text>\\n   <text x='262.66' y='75.79' font-size='10.67pt' font-weight='bold' font-family='IBM Plex Sans' fill='#FFFFFF' fill-opacity='1'>Harris<\\/text>\\n   <text x='267.76' y='96.28' font-size='10.67pt' font-weight='bold' font-family='IBM Plex Sans' fill='#FFFFFF' fill-opacity='1'>81%<\\/text>\\n   <text x='262.23' y='75.15' font-size='10.67pt' font-weight='bold' font-family='IBM Plex Sans' fill='#FFFFFF' fill-opacity='1'>Harris<\\/text>\\n   <text x='267.33' y='95.64' font-size='10.67pt' font-weight='bold' font-family='IBM Plex Sans' fill='#FFFFFF' fill-opacity='1'>81%<\\/text>\\n   <text x='261.59' y='74.72' font-size='10.67pt' font-weight='bold' font-family='IBM Plex Sans' fill='#FFFFFF' fill-opacity='1'>Harris<\\/text>\\n   <text x='266.69' y='95.21' font-size='10.67pt' font-weight='bold' font-family='IBM Plex Sans' fill='#FFFFFF' fill-opacity='1'>81%<\\/text>\\n   <text x='260.83' y='74.57' font-size='10.67pt' font-weight='bold' font-family='IBM Plex Sans' fill='#FFFFFF' fill-opacity='1'>Harris<\\/text>\\n   <text x='265.93' y='95.05' font-size='10.67pt' font-weight='bold' font-family='IBM Plex Sans' fill='#FFFFFF' fill-opacity='1'>81%<\\/text>\\n   <text x='260.07' y='74.72' font-size='10.67pt' font-weight='bold' font-family='IBM Plex Sans' fill='#FFFFFF' fill-opacity='1'>Harris<\\/text>\\n   <text x='265.17' y='95.21' font-size='10.67pt' font-weight='bold' font-family='IBM Plex Sans' fill='#FFFFFF' fill-opacity='1'>81%<\\/text>\\n   <text x='259.43' y='75.15' font-size='10.67pt' font-weight='bold' font-family='IBM Plex Sans' fill='#FFFFFF' fill-opacity='1'>Harris<\\/text>\\n   <text x='264.52' y='95.64' font-size='10.67pt' font-weight='bold' font-family='IBM Plex Sans' fill='#FFFFFF' fill-opacity='1'>81%<\\/text>\\n   <text x='259' y='75.79' font-size='10.67pt' font-weight='bold' font-family='IBM Plex Sans' fill='#FFFFFF' fill-opacity='1'>Harris<\\/text>\\n   <text x='264.09' y='96.28' font-size='10.67pt' font-weight='bold' font-family='IBM Plex Sans' fill='#FFFFFF' fill-opacity='1'>81%<\\/text>\\n   <text x='258.84' y='76.55' font-size='10.67pt' font-weight='bold' font-family='IBM Plex Sans' fill='#FFFFFF' fill-opacity='1'>Harris<\\/text>\\n   <text x='263.94' y='97.04' font-size='10.67pt' font-weight='bold' font-family='IBM Plex Sans' fill='#FFFFFF' fill-opacity='1'>81%<\\/text>\\n   <text x='259' y='77.31' font-size='10.67pt' font-weight='bold' font-family='IBM Plex Sans' fill='#FFFFFF' fill-opacity='1'>Harris<\\/text>\\n   <text x='264.09' y='97.8' font-size='10.67pt' font-weight='bold' font-family='IBM Plex Sans' fill='#FFFFFF' fill-opacity='1'>81%<\\/text>\\n   <text x='259.43' y='77.96' font-size='10.67pt' font-weight='bold' font-family='IBM Plex Sans' fill='#FFFFFF' fill-opacity='1'>Harris<\\/text>\\n   <text x='264.52' y='98.44' font-size='10.67pt' font-weight='bold' font-family='IBM Plex Sans' fill='#FFFFFF' fill-opacity='1'>81%<\\/text>\\n   <text x='260.07' y='78.39' font-size='10.67pt' font-weight='bold' font-family='IBM Plex Sans' fill='#FFFFFF' fill-opacity='1'>Harris<\\/text>\\n   <text x='265.17' y='98.87' font-size='10.67pt' font-weight='bold' font-family='IBM Plex Sans' fill='#FFFFFF' fill-opacity='1'>81%<\\/text>\\n   <text x='260.83' y='78.54' font-size='10.67pt' font-weight='bold' font-family='IBM Plex Sans' fill='#FFFFFF' fill-opacity='1'>Harris<\\/text>\\n   <text x='265.93' y='99.03' font-size='10.67pt' font-weight='bold' font-family='IBM Plex Sans' fill='#FFFFFF' fill-opacity='1'>81%<\\/text>\\n   <text x='261.59' y='78.39' font-size='10.67pt' font-weight='bold' font-family='IBM Plex Sans' fill='#FFFFFF' fill-opacity='1'>Harris<\\/text>\\n   <text x='266.69' y='98.87' font-size='10.67pt' font-weight='bold' font-family='IBM Plex Sans' fill='#FFFFFF' fill-opacity='1'>81%<\\/text>\\n   <text x='262.23' y='77.96' font-size='10.67pt' font-weight='bold' font-family='IBM Plex Sans' fill='#FFFFFF' fill-opacity='1'>Harris<\\/text>\\n   <text x='267.33' y='98.44' font-size='10.67pt' font-weight='bold' font-family='IBM Plex Sans' fill='#FFFFFF' fill-opacity='1'>81%<\\/text>\\n   <text x='262.66' y='77.31' font-size='10.67pt' font-weight='bold' font-family='IBM Plex Sans' fill='#FFFFFF' fill-opacity='1'>Harris<\\/text>\\n   <text x='267.76' y='97.8' font-size='10.67pt' font-weight='bold' font-family='IBM Plex Sans' fill='#FFFFFF' fill-opacity='1'>81%<\\/text>\\n   <text x='262.82' y='76.55' font-size='10.67pt' font-weight='bold' font-family='IBM Plex Sans' fill='#FFFFFF' fill-opacity='1'>Harris<\\/text>\\n   <text x='267.91' y='97.04' font-size='10.67pt' font-weight='bold' font-family='IBM Plex Sans' fill='#FFFFFF' fill-opacity='1'>81%<\\/text>\\n   <text x='260.83' y='76.55' font-size='10.67pt' font-weight='bold' font-family='IBM Plex Sans' fill='#3579AC' fill-opacity='1'>Harris<\\/text>\\n   <text x='265.93' y='97.04' font-size='10.67pt' font-weight='bold' font-family='IBM Plex Sans' fill='#3579AC' fill-opacity='1'>81%<\\/text>\\n   <rect id='svg_171e6422_7ffe_43c2_b5d0_9cbaf74be05d_e1' x='91.33' y='36.7' width='7.17' height='232.78' fill='#333333' fill-opacity='0' stroke='none' title='August 1st&amp;lt;br&amp;gt;Harris: &amp;lt;span style=&amp;#39;float:right;&amp;#39;&amp;gt;75%&amp;lt;/span&amp;gt;&amp;lt;br&amp;gt;Trump: &amp;lt;span style=&amp;#39;float:right;&amp;#39;&amp;gt;25%&amp;lt;/span&amp;gt;'/>\\n   <rect id='svg_171e6422_7ffe_43c2_b5d0_9cbaf74be05d_e2' x='98.5' y='36.7' width='7.17' height='232.78' fill='#333333' fill-opacity='0' stroke='none' title='August 2nd&amp;lt;br&amp;gt;Harris: &amp;lt;span style=&amp;#39;float:right;&amp;#39;&amp;gt;74%&amp;lt;/span&amp;gt;&amp;lt;br&amp;gt;Trump: &amp;lt;span style=&amp;#39;float:right;&amp;#39;&amp;gt;26%&amp;lt;/span&amp;gt;'/>\\n   <rect id='svg_171e6422_7ffe_43c2_b5d0_9cbaf74be05d_e3' x='105.67' y='36.7' width='7.17' height='232.78' fill='#333333' fill-opacity='0' stroke='none' title='August 3rd&amp;lt;br&amp;gt;Harris: &amp;lt;span style=&amp;#39;float:right;&amp;#39;&amp;gt;74%&amp;lt;/span&amp;gt;&amp;lt;br&amp;gt;Trump: &amp;lt;span style=&amp;#39;float:right;&amp;#39;&amp;gt;26%&amp;lt;/span&amp;gt;'/>\\n   <rect id='svg_171e6422_7ffe_43c2_b5d0_9cbaf74be05d_e4' x='112.84' y='36.7' width='7.17' height='232.78' fill='#333333' fill-opacity='0' stroke='none' title='August 4th&amp;lt;br&amp;gt;Harris: &amp;lt;span style=&amp;#39;float:right;&amp;#39;&amp;gt;77%&amp;lt;/span&amp;gt;&amp;lt;br&amp;gt;Trump: &amp;lt;span style=&amp;#39;float:right;&amp;#39;&amp;gt;23%&amp;lt;/span&amp;gt;'/>\\n   <rect id='svg_171e6422_7ffe_43c2_b5d0_9cbaf74be05d_e5' x='120.01' y='36.7' width='7.17' height='232.78' fill='#333333' fill-opacity='0' stroke='none' title='August 5th&amp;lt;br&amp;gt;Harris: &amp;lt;span style=&amp;#39;float:right;&amp;#39;&amp;gt;76%&amp;lt;/span&amp;gt;&amp;lt;br&amp;gt;Trump: &amp;lt;span style=&amp;#39;float:right;&amp;#39;&amp;gt;24%&amp;lt;/span&amp;gt;'/>\\n   <rect id='svg_171e6422_7ffe_43c2_b5d0_9cbaf74be05d_e6' x='127.19' y='36.7' width='7.17' height='232.78' fill='#333333' fill-opacity='0' stroke='none' title='August 6th&amp;lt;br&amp;gt;Harris: &amp;lt;span style=&amp;#39;float:right;&amp;#39;&amp;gt;77%&amp;lt;/span&amp;gt;&amp;lt;br&amp;gt;Trump: &amp;lt;span style=&amp;#39;float:right;&amp;#39;&amp;gt;23%&amp;lt;/span&amp;gt;'/>\\n   <rect id='svg_171e6422_7ffe_43c2_b5d0_9cbaf74be05d_e7' x='134.36' y='36.7' width='7.17' height='232.78' fill='#333333' fill-opacity='0' stroke='none' title='August 7th&amp;lt;br&amp;gt;Harris: &amp;lt;span style=&amp;#39;float:right;&amp;#39;&amp;gt;78%&amp;lt;/span&amp;gt;&amp;lt;br&amp;gt;Trump: &amp;lt;span style=&amp;#39;float:right;&amp;#39;&amp;gt;22%&amp;lt;/span&amp;gt;'/>\\n   <rect id='svg_171e6422_7ffe_43c2_b5d0_9cbaf74be05d_e8' x='141.53' y='36.7' width='7.17' height='232.78' fill='#333333' fill-opacity='0' stroke='none' title='August 8th&amp;lt;br&amp;gt;Harris: &amp;lt;span style=&amp;#39;float:right;&amp;#39;&amp;gt;78%&amp;lt;/span&amp;gt;&amp;lt;br&amp;gt;Trump: &amp;lt;span style=&amp;#39;float:right;&amp;#39;&amp;gt;22%&amp;lt;/span&amp;gt;'/>\\n   <rect id='svg_171e6422_7ffe_43c2_b5d0_9cbaf74be05d_e9' x='148.7' y='36.7' width='7.17' height='232.78' fill='#333333' fill-opacity='0' stroke='none' title='August 9th&amp;lt;br&amp;gt;Harris: &amp;lt;span style=&amp;#39;float:right;&amp;#39;&amp;gt;78%&amp;lt;/span&amp;gt;&amp;lt;br&amp;gt;Trump: &amp;lt;span style=&amp;#39;float:right;&amp;#39;&amp;gt;22%&amp;lt;/span&amp;gt;'/>\\n   <rect id='svg_171e6422_7ffe_43c2_b5d0_9cbaf74be05d_e10' x='155.87' y='36.7' width='7.17' height='232.78' fill='#333333' fill-opacity='0' stroke='none' title='August 10th&amp;lt;br&amp;gt;Harris: &amp;lt;span style=&amp;#39;float:right;&amp;#39;&amp;gt;78%&amp;lt;/span&amp;gt;&amp;lt;br&amp;gt;Trump: &amp;lt;span style=&amp;#39;float:right;&amp;#39;&amp;gt;22%&amp;lt;/span&amp;gt;'/>\\n   <rect id='svg_171e6422_7ffe_43c2_b5d0_9cbaf74be05d_e11' x='163.05' y='36.7' width='7.17' height='232.78' fill='#333333' fill-opacity='0' stroke='none' title='August 11th&amp;lt;br&amp;gt;Harris: &amp;lt;span style=&amp;#39;float:right;&amp;#39;&amp;gt;78%&amp;lt;/span&amp;gt;&amp;lt;br&amp;gt;Trump: &amp;lt;span style=&amp;#39;float:right;&amp;#39;&amp;gt;22%&amp;lt;/span&amp;gt;'/>\\n   <rect id='svg_171e6422_7ffe_43c2_b5d0_9cbaf74be05d_e12' x='170.22' y='36.7' width='7.17' height='232.78' fill='#333333' fill-opacity='0' stroke='none' title='August 12th&amp;lt;br&amp;gt;Harris: &amp;lt;span style=&amp;#39;float:right;&amp;#39;&amp;gt;79%&amp;lt;/span&amp;gt;&amp;lt;br&amp;gt;Trump: &amp;lt;span style=&amp;#39;float:right;&amp;#39;&amp;gt;21%&amp;lt;/span&amp;gt;'/>\\n   <rect id='svg_171e6422_7ffe_43c2_b5d0_9cbaf74be05d_e13' x='177.39' y='36.7' width='7.17' height='232.78' fill='#333333' fill-opacity='0' stroke='none' title='August 13th&amp;lt;br&amp;gt;Harris: &amp;lt;span style=&amp;#39;float:right;&amp;#39;&amp;gt;79%&amp;lt;/span&amp;gt;&amp;lt;br&amp;gt;Trump: &amp;lt;span style=&amp;#39;float:right;&amp;#39;&amp;gt;21%&amp;lt;/span&amp;gt;'/>\\n   <rect id='svg_171e6422_7ffe_43c2_b5d0_9cbaf74be05d_e14' x='184.56' y='36.7' width='7.17' height='232.78' fill='#333333' fill-opacity='0' stroke='none' title='August 14th&amp;lt;br&amp;gt;Harris: &amp;lt;span style=&amp;#39;float:right;&amp;#39;&amp;gt;79%&amp;lt;/span&amp;gt;&amp;lt;br&amp;gt;Trump: &amp;lt;span style=&amp;#39;float:right;&amp;#39;&amp;gt;21%&amp;lt;/span&amp;gt;'/>\\n   <rect id='svg_171e6422_7ffe_43c2_b5d0_9cbaf74be05d_e15' x='191.73' y='36.7' width='7.17' height='232.78' fill='#333333' fill-opacity='0' stroke='none' title='August 15th&amp;lt;br&amp;gt;Harris: &amp;lt;span style=&amp;#39;float:right;&amp;#39;&amp;gt;79%&amp;lt;/span&amp;gt;&amp;lt;br&amp;gt;Trump: &amp;lt;span style=&amp;#39;float:right;&amp;#39;&amp;gt;21%&amp;lt;/span&amp;gt;'/>\\n   <rect id='svg_171e6422_7ffe_43c2_b5d0_9cbaf74be05d_e16' x='198.91' y='36.7' width='7.17' height='232.78' fill='#333333' fill-opacity='0' stroke='none' title='August 16th&amp;lt;br&amp;gt;Harris: &amp;lt;span style=&amp;#39;float:right;&amp;#39;&amp;gt;79%&amp;lt;/span&amp;gt;&amp;lt;br&amp;gt;Trump: &amp;lt;span style=&amp;#39;float:right;&amp;#39;&amp;gt;21%&amp;lt;/span&amp;gt;'/>\\n   <rect id='svg_171e6422_7ffe_43c2_b5d0_9cbaf74be05d_e17' x='206.08' y='36.7' width='7.17' height='232.78' fill='#333333' fill-opacity='0' stroke='none' title='August 17th&amp;lt;br&amp;gt;Harris: &amp;lt;span style=&amp;#39;float:right;&amp;#39;&amp;gt;78%&amp;lt;/span&amp;gt;&amp;lt;br&amp;gt;Trump: &amp;lt;span style=&amp;#39;float:right;&amp;#39;&amp;gt;22%&amp;lt;/span&amp;gt;'/>\\n   <rect id='svg_171e6422_7ffe_43c2_b5d0_9cbaf74be05d_e18' x='213.25' y='36.7' width='7.17' height='232.78' fill='#333333' fill-opacity='0' stroke='none' title='August 18th&amp;lt;br&amp;gt;Harris: &amp;lt;span style=&amp;#39;float:right;&amp;#39;&amp;gt;78%&amp;lt;/span&amp;gt;&amp;lt;br&amp;gt;Trump: &amp;lt;span style=&amp;#39;float:right;&amp;#39;&amp;gt;22%&amp;lt;/span&amp;gt;'/>\\n   <rect id='svg_171e6422_7ffe_43c2_b5d0_9cbaf74be05d_e19' x='220.42' y='36.7' width='7.17' height='232.78' fill='#333333' fill-opacity='0' stroke='none' title='August 19th&amp;lt;br&amp;gt;Harris: &amp;lt;span style=&amp;#39;float:right;&amp;#39;&amp;gt;78%&amp;lt;/span&amp;gt;&amp;lt;br&amp;gt;Trump: &amp;lt;span style=&amp;#39;float:right;&amp;#39;&amp;gt;22%&amp;lt;/span&amp;gt;'/>\\n   <rect id='svg_171e6422_7ffe_43c2_b5d0_9cbaf74be05d_e20' x='227.6' y='36.7' width='7.17' height='232.78' fill='#333333' fill-opacity='0' stroke='none' title='August 20th&amp;lt;br&amp;gt;Harris: &amp;lt;span style=&amp;#39;float:right;&amp;#39;&amp;gt;80%&amp;lt;/span&amp;gt;&amp;lt;br&amp;gt;Trump: &amp;lt;span style=&amp;#39;float:right;&amp;#39;&amp;gt;20%&amp;lt;/span&amp;gt;'/>\\n   <rect id='svg_171e6422_7ffe_43c2_b5d0_9cbaf74be05d_e21' x='234.77' y='36.7' width='7.17' height='232.78' fill='#333333' fill-opacity='0' stroke='none' title='August 21st&amp;lt;br&amp;gt;Harris: &amp;lt;span style=&amp;#39;float:right;&amp;#39;&amp;gt;79%&amp;lt;/span&amp;gt;&amp;lt;br&amp;gt;Trump: &amp;lt;span style=&amp;#39;float:right;&amp;#39;&amp;gt;21%&amp;lt;/span&amp;gt;'/>\\n   <rect id='svg_171e6422_7ffe_43c2_b5d0_9cbaf74be05d_e22' x='241.94' y='36.7' width='7.17' height='232.78' fill='#333333' fill-opacity='0' stroke='none' title='August 22nd&amp;lt;br&amp;gt;Harris: &amp;lt;span style=&amp;#39;float:right;&amp;#39;&amp;gt;81%&amp;lt;/span&amp;gt;&amp;lt;br&amp;gt;Trump: &amp;lt;span style=&amp;#39;float:right;&amp;#39;&amp;gt;19%&amp;lt;/span&amp;gt;'/>\\n  <\\/g>\\n <\\/g>\\n<\\/svg>\",\"js\":null,\"uid\":\"svg_171e6422_7ffe_43c2_b5d0_9cbaf74be05d\",\"ratio\":3,\"settings\":{\"tooltip\":{\"css\":\".tooltip_SVGID_ { font-family:IBM Plex Sans;color:#363a3c;background-color:#fafafa;padding:5px;border-radius:3px;border-color:black;border-style:solid;border-width:0.125em 0em 0em 0em;box-shadow: 0px 0px 10px 5px lightgray;min-width: 120px ; position:absolute;pointer-events:none;z-index:999;}\",\"placement\":\"doc\",\"opacity\":1,\"offx\":10,\"offy\":0,\"use_cursor_pos\":true,\"use_fill\":false,\"use_stroke\":false,\"delay_over\":200,\"delay_out\":500},\"hover\":{\"css\":\".hover_data_SVGID_ { fill:orange;stroke:black;cursor:pointer; }\\ntext.hover_data_SVGID_ { stroke:none;fill:orange; }\\ncircle.hover_data_SVGID_ { fill:orange;stroke:black; }\\nline.hover_data_SVGID_, polyline.hover_data_SVGID_ { fill:none;stroke:orange; }\\nrect.hover_data_SVGID_, polygon.hover_data_SVGID_, path.hover_data_SVGID_ { fill:orange;stroke:none; }\\nimage.hover_data_SVGID_ { stroke:orange; }\",\"reactive\":true,\"nearest_distance\":null},\"hover_inv\":{\"css\":\"\"},\"hover_key\":{\"css\":\".hover_key_SVGID_ { fill:orange;stroke:black;cursor:pointer; }\\ntext.hover_key_SVGID_ { stroke:none;fill:orange; }\\ncircle.hover_key_SVGID_ { fill:orange;stroke:black; }\\nline.hover_key_SVGID_, polyline.hover_key_SVGID_ { fill:none;stroke:orange; }\\nrect.hover_key_SVGID_, polygon.hover_key_SVGID_, path.hover_key_SVGID_ { fill:orange;stroke:none; }\\nimage.hover_key_SVGID_ { stroke:orange; }\",\"reactive\":true},\"hover_theme\":{\"css\":\".hover_theme_SVGID_ { fill:orange;stroke:black;cursor:pointer; }\\ntext.hover_theme_SVGID_ { stroke:none;fill:orange; }\\ncircle.hover_theme_SVGID_ { fill:orange;stroke:black; }\\nline.hover_theme_SVGID_, polyline.hover_theme_SVGID_ { fill:none;stroke:orange; }\\nrect.hover_theme_SVGID_, polygon.hover_theme_SVGID_, path.hover_theme_SVGID_ { fill:orange;stroke:none; }\\nimage.hover_theme_SVGID_ { stroke:orange; }\",\"reactive\":true},\"select\":{\"css\":\".select_data_SVGID_ { fill:red;stroke:black;cursor:pointer; }\\ntext.select_data_SVGID_ { stroke:none;fill:red; }\\ncircle.select_data_SVGID_ { fill:red;stroke:black; }\\nline.select_data_SVGID_, polyline.select_data_SVGID_ { fill:none;stroke:red; }\\nrect.select_data_SVGID_, polygon.select_data_SVGID_, path.select_data_SVGID_ { fill:red;stroke:none; }\\nimage.select_data_SVGID_ { stroke:red; }\",\"type\":\"multiple\",\"only_shiny\":true,\"selected\":[]},\"select_inv\":{\"css\":\"\"},\"select_key\":{\"css\":\".select_key_SVGID_ { fill:red;stroke:black;cursor:pointer; }\\ntext.select_key_SVGID_ { stroke:none;fill:red; }\\ncircle.select_key_SVGID_ { fill:red;stroke:black; }\\nline.select_key_SVGID_, polyline.select_key_SVGID_ { fill:none;stroke:red; }\\nrect.select_key_SVGID_, polygon.select_key_SVGID_, path.select_key_SVGID_ { fill:red;stroke:none; }\\nimage.select_key_SVGID_ { stroke:red; }\",\"type\":\"single\",\"only_shiny\":true,\"selected\":[]},\"select_theme\":{\"css\":\".select_theme_SVGID_ { fill:red;stroke:black;cursor:pointer; }\\ntext.select_theme_SVGID_ { stroke:none;fill:red; }\\ncircle.select_theme_SVGID_ { fill:red;stroke:black; }\\nline.select_theme_SVGID_, polyline.select_theme_SVGID_ { fill:none;stroke:red; }\\nrect.select_theme_SVGID_, polygon.select_theme_SVGID_, path.select_theme_SVGID_ { fill:red;stroke:none; }\\nimage.select_theme_SVGID_ { stroke:red; }\",\"type\":\"single\",\"only_shiny\":true,\"selected\":[]},\"zoom\":{\"min\":1,\"max\":1,\"duration\":300},\"toolbar\":{\"position\":\"topright\",\"pngname\":\"diagram\",\"tooltips\":null,\"fixed\":false,\"hidden\":[],\"delay_over\":200,\"delay_out\":500},\"sizing\":{\"rescale\":true,\"width\":1}}},\"evals\":[],\"jsHooks\":[]}</script>\n```\n\n:::\n:::\n\n\n\n---\n\n:::: {.columns}\n::: {.column width=\"60%\"}\n\n\n### <span style='font-family:Playfair Display;'>Forecasted election-day voteshare</span>\nThe model first constructs a polling average, pooling data across similar states when polls are sparse.\nIt then projects forward to election day, initially relying on non-polling indicators like economic growth and partisanship, but aligning more closely with the polling average as election day approaches.\n\n\n:::\n::: {.column width=\"40%\"}\n:::\n::::\n\n\n\n::: {.cell}\n::: {.cell-output-display}\n\n```{=html}\n<div class=\"girafe html-widget html-fill-item\" id=\"htmlwidget-abef0209369ca1262390\" style=\"width:100%;height:216px;\"></div>\n<script type=\"application/json\" data-for=\"htmlwidget-abef0209369ca1262390\">{\"x\":{\"html\":\"<?xml version=\\\"1.0\\\" encoding=\\\"UTF-8\\\"?>\\n<svg xmlns='http://www.w3.org/2000/svg' xmlns:xlink='http://www.w3.org/1999/xlink' class='ggiraph-svg' role='graphics-document' id='svg_9ecb741d_d9b0_4769_8c13_9345064f3834' viewBox='0 0 864 288'>\\n <defs id='svg_9ecb741d_d9b0_4769_8c13_9345064f3834_defs'>\\n  <clipPath id='svg_9ecb741d_d9b0_4769_8c13_9345064f3834_c1'>\\n   <rect x='0' y='0' width='864' height='288'/>\\n  <\\/clipPath>\\n  <clipPath id='svg_9ecb741d_d9b0_4769_8c13_9345064f3834_c2'>\\n   <rect x='5.98' y='5.98' width='852.04' height='276.04'/>\\n  <\\/clipPath>\\n <\\/defs>\\n <g id='svg_9ecb741d_d9b0_4769_8c13_9345064f3834_rootg' class='ggiraph-svg-rootg'>\\n  <g clip-path='url(#svg_9ecb741d_d9b0_4769_8c13_9345064f3834_c1)'>\\n   <rect x='0' y='0' width='864' height='288' fill='#FFFFFF' fill-opacity='1' stroke='#FFFFFF' stroke-opacity='1' stroke-width='0.75' stroke-linejoin='round' stroke-linecap='round' class='ggiraph-svg-bg'/>\\n   <rect x='0' y='0' width='864' height='288' fill='#FFFFFF' fill-opacity='1' stroke='#FFFFFF' stroke-opacity='1' stroke-width='1.16' stroke-linejoin='round' stroke-linecap='round'/>\\n  <\\/g>\\n  <g clip-path='url(#svg_9ecb741d_d9b0_4769_8c13_9345064f3834_c2)'>\\n   <polyline points='5.98,258.61 858.02,258.61' fill='none' stroke='#EBEBEB' stroke-opacity='1' stroke-width='0.53' stroke-linejoin='round' stroke-linecap='butt'/>\\n   <polyline points='5.98,223.44 858.02,223.44' fill='none' stroke='#EBEBEB' stroke-opacity='1' stroke-width='0.53' stroke-linejoin='round' stroke-linecap='butt'/>\\n   <polyline points='5.98,188.26 858.02,188.26' fill='none' stroke='#EBEBEB' stroke-opacity='1' stroke-width='0.53' stroke-linejoin='round' stroke-linecap='butt'/>\\n   <polyline points='5.98,153.09 858.02,153.09' fill='none' stroke='#EBEBEB' stroke-opacity='1' stroke-width='0.53' stroke-linejoin='round' stroke-linecap='butt'/>\\n   <polyline points='5.98,117.91 858.02,117.91' fill='none' stroke='#EBEBEB' stroke-opacity='1' stroke-width='0.53' stroke-linejoin='round' stroke-linecap='butt'/>\\n   <polyline points='5.98,82.74 858.02,82.74' fill='none' stroke='#EBEBEB' stroke-opacity='1' stroke-width='0.53' stroke-linejoin='round' stroke-linecap='butt'/>\\n   <polyline points='5.98,47.56 858.02,47.56' fill='none' stroke='#EBEBEB' stroke-opacity='1' stroke-width='0.53' stroke-linejoin='round' stroke-linecap='butt'/>\\n  <\\/g>\\n  <g clip-path='url(#svg_9ecb741d_d9b0_4769_8c13_9345064f3834_c1)'>\\n   <polyline points='94.91,272.46 94.91,269.47' fill='none' stroke='#000000' stroke-opacity='1' stroke-width='1.16' stroke-linejoin='round' stroke-linecap='butt'/>\\n   <polyline points='317.25,272.46 317.25,269.47' fill='none' stroke='#000000' stroke-opacity='1' stroke-width='1.16' stroke-linejoin='round' stroke-linecap='butt'/>\\n   <polyline points='532.41,272.46 532.41,269.47' fill='none' stroke='#000000' stroke-opacity='1' stroke-width='1.16' stroke-linejoin='round' stroke-linecap='butt'/>\\n   <polyline points='754.74,272.46 754.74,269.47' fill='none' stroke='#000000' stroke-opacity='1' stroke-width='1.16' stroke-linejoin='round' stroke-linecap='butt'/>\\n   <text x='79.83' y='281.55' font-size='7.2pt' font-family='IBM Plex Sans' fill='#363A3C' fill-opacity='1'>August<\\/text>\\n   <text x='293.37' y='281.55' font-size='7.2pt' font-family='IBM Plex Sans' fill='#363A3C' fill-opacity='1'>September<\\/text>\\n   <text x='515.06' y='281.55' font-size='7.2pt' font-family='IBM Plex Sans' fill='#363A3C' fill-opacity='1'>October<\\/text>\\n   <text x='732.32' y='281.55' font-size='7.2pt' font-family='IBM Plex Sans' fill='#363A3C' fill-opacity='1'>November<\\/text>\\n   <text x='11.36' y='252.22' font-size='7.2pt' font-family='IBM Plex Sans' fill='#363A3C' fill-opacity='1'>35%<\\/text>\\n   <text x='11.36' y='217.04' font-size='7.2pt' font-family='IBM Plex Sans' fill='#363A3C' fill-opacity='1'>40%<\\/text>\\n   <text x='11.36' y='181.87' font-size='7.2pt' font-family='IBM Plex Sans' fill='#363A3C' fill-opacity='1'>45%<\\/text>\\n   <text x='11.36' y='146.69' font-size='7.2pt' font-family='IBM Plex Sans' fill='#363A3C' fill-opacity='1'>50%<\\/text>\\n   <text x='11.36' y='111.52' font-size='7.2pt' font-family='IBM Plex Sans' fill='#363A3C' fill-opacity='1'>55%<\\/text>\\n   <text x='11.36' y='76.34' font-size='7.2pt' font-family='IBM Plex Sans' fill='#363A3C' fill-opacity='1'>60%<\\/text>\\n   <text x='11.36' y='41.17' font-size='7.2pt' font-family='IBM Plex Sans' fill='#363A3C' fill-opacity='1'>65%<\\/text>\\n  <\\/g>\\n  <g clip-path='url(#svg_9ecb741d_d9b0_4769_8c13_9345064f3834_c2)'>\\n   <line x1='5.98' y1='153.09' x2='858.02' y2='153.09' stroke='#363A3C' stroke-opacity='1' stroke-width='0.64' stroke-linejoin='round' stroke-linecap='butt'/>\\n   <polygon points='94.91,115.61 102.08,115.56 109.26,114.66 116.43,117.92 123.60,117.18 130.77,118.44 137.94,117.68 145.12,118.53 152.29,119.66 159.46,118.04 166.63,119.82 173.80,120.14 180.98,121.37 188.15,121.16 195.32,120.12 202.49,121.92 209.67,120.46 216.84,120.99 224.01,121.77 231.18,122.87 238.35,122.77 245.53,123.64 245.53,258.89 238.35,257.53 231.18,255.03 224.01,252.55 216.84,249.48 209.67,250.75 202.49,251.86 195.32,251.98 188.15,252.95 180.98,256.50 173.80,256.46 166.63,257.57 159.46,251.49 152.29,256.06 145.12,253.51 137.94,254.55 130.77,254.51 123.60,253.01 116.43,250.04 109.26,252.10 102.08,247.61 94.91,249.24' fill='#B13737' fill-opacity='0.13' stroke='none'/>\\n   <polyline points='94.91,115.61 102.08,115.56 109.26,114.66 116.43,117.92 123.60,117.18 130.77,118.44 137.94,117.68 145.12,118.53 152.29,119.66 159.46,118.04 166.63,119.82 173.80,120.14 180.98,121.37 188.15,121.16 195.32,120.12 202.49,121.92 209.67,120.46 216.84,120.99 224.01,121.77 231.18,122.87 238.35,122.77 245.53,123.64' fill='none' stroke='none'/>\\n   <polyline points='245.53,258.89 238.35,257.53 231.18,255.03 224.01,252.55 216.84,249.48 209.67,250.75 202.49,251.86 195.32,251.98 188.15,252.95 180.98,256.50 173.80,256.46 166.63,257.57 159.46,251.49 152.29,256.06 145.12,253.51 137.94,254.55 130.77,254.51 123.60,253.01 116.43,250.04 109.26,252.10 102.08,247.61 94.91,249.24' fill='none' stroke='none'/>\\n   <polygon points='94.91,143.87 102.08,144.77 109.26,144.55 116.43,146.30 123.60,145.96 130.77,146.89 137.94,147.39 145.12,147.74 152.29,147.80 159.46,147.56 166.63,147.80 173.80,149.05 180.98,148.99 188.15,149.01 195.32,148.44 202.49,149.18 209.67,147.93 216.84,148.29 224.01,148.15 231.18,150.00 238.35,149.42 245.53,150.59 245.53,212.37 238.35,210.89 231.18,210.66 224.01,208.70 216.84,209.52 209.67,208.24 202.49,210.05 195.32,208.92 188.15,210.18 180.98,211.75 173.80,210.57 166.63,210.52 159.46,208.02 152.29,209.99 145.12,210.20 137.94,210.54 130.77,209.85 123.60,207.87 116.43,206.23 109.26,207.49 102.08,205.96 94.91,205.92' fill='#B13737' fill-opacity='0.13' stroke='none'/>\\n   <polyline points='94.91,143.87 102.08,144.77 109.26,144.55 116.43,146.30 123.60,145.96 130.77,146.89 137.94,147.39 145.12,147.74 152.29,147.80 159.46,147.56 166.63,147.80 173.80,149.05 180.98,148.99 188.15,149.01 195.32,148.44 202.49,149.18 209.67,147.93 216.84,148.29 224.01,148.15 231.18,150.00 238.35,149.42 245.53,150.59' fill='none' stroke='none'/>\\n   <polyline points='245.53,212.37 238.35,210.89 231.18,210.66 224.01,208.70 216.84,209.52 209.67,208.24 202.49,210.05 195.32,208.92 188.15,210.18 180.98,211.75 173.80,210.57 166.63,210.52 159.46,208.02 152.29,209.99 145.12,210.20 137.94,210.54 130.77,209.85 123.60,207.87 116.43,206.23 109.26,207.49 102.08,205.96 94.91,205.92' fill='none' stroke='none'/>\\n   <polygon points='94.91,56.93 102.08,58.57 109.26,54.07 116.43,56.13 123.60,53.16 130.77,51.66 137.94,51.63 145.12,52.66 152.29,50.11 159.46,54.68 166.63,48.60 173.80,49.71 180.98,49.67 188.15,53.22 195.32,54.19 202.49,54.31 209.67,55.42 216.84,56.69 224.01,53.62 231.18,51.14 238.35,48.65 245.53,47.28 245.53,182.53 238.35,183.40 231.18,183.30 224.01,184.40 216.84,185.18 209.67,185.72 202.49,184.26 195.32,186.05 188.15,185.01 180.98,184.80 173.80,186.03 166.63,186.36 159.46,188.14 152.29,186.51 145.12,187.64 137.94,188.49 130.77,187.73 123.60,188.99 116.43,188.25 109.26,191.52 102.08,190.61 94.91,190.56' fill='#3579AC' fill-opacity='0.13' stroke='none'/>\\n   <polyline points='94.91,56.93 102.08,58.57 109.26,54.07 116.43,56.13 123.60,53.16 130.77,51.66 137.94,51.63 145.12,52.66 152.29,50.11 159.46,54.68 166.63,48.60 173.80,49.71 180.98,49.67 188.15,53.22 195.32,54.19 202.49,54.31 209.67,55.42 216.84,56.69 224.01,53.62 231.18,51.14 238.35,48.65 245.53,47.28' fill='none' stroke='none'/>\\n   <polyline points='245.53,182.53 238.35,183.40 231.18,183.30 224.01,184.40 216.84,185.18 209.67,185.72 202.49,184.26 195.32,186.05 188.15,185.01 180.98,184.80 173.80,186.03 166.63,186.36 159.46,188.14 152.29,186.51 145.12,187.64 137.94,188.49 130.77,187.73 123.60,188.99 116.43,188.25 109.26,191.52 102.08,190.61 94.91,190.56' fill='none' stroke='none'/>\\n   <polygon points='94.91,100.25 102.08,100.21 109.26,98.68 116.43,99.95 123.60,98.30 130.77,96.33 137.94,95.63 145.12,95.97 152.29,96.18 159.46,98.16 166.63,95.66 173.80,95.61 180.98,94.42 188.15,96.00 195.32,97.25 202.49,96.12 209.67,97.93 216.84,96.65 224.01,97.48 231.18,95.51 238.35,95.28 245.53,93.80 245.53,155.58 238.35,156.76 231.18,156.17 224.01,158.02 216.84,157.89 209.67,158.24 202.49,156.99 195.32,157.73 188.15,157.17 180.98,157.18 173.80,157.13 166.63,158.37 159.46,158.61 152.29,158.38 145.12,158.43 137.94,158.78 130.77,159.28 123.60,160.21 116.43,159.87 109.26,161.62 102.08,161.41 94.91,162.30' fill='#3579AC' fill-opacity='0.13' stroke='none'/>\\n   <polyline points='94.91,100.25 102.08,100.21 109.26,98.68 116.43,99.95 123.60,98.30 130.77,96.33 137.94,95.63 145.12,95.97 152.29,96.18 159.46,98.16 166.63,95.66 173.80,95.61 180.98,94.42 188.15,96.00 195.32,97.25 202.49,96.12 209.67,97.93 216.84,96.65 224.01,97.48 231.18,95.51 238.35,95.28 245.53,93.80' fill='none' stroke='none'/>\\n   <polyline points='245.53,155.58 238.35,156.76 231.18,156.17 224.01,158.02 216.84,157.89 209.67,158.24 202.49,156.99 195.32,157.73 188.15,157.17 180.98,157.18 173.80,157.13 166.63,158.37 159.46,158.61 152.29,158.38 145.12,158.43 137.94,158.78 130.77,159.28 123.60,160.21 116.43,159.87 109.26,161.62 102.08,161.41 94.91,162.30' fill='none' stroke='none'/>\\n   <line x1='783.43' y1='269.47' x2='783.43' y2='27.18' stroke='#333333' stroke-opacity='1' stroke-width='0.85' stroke-linejoin='round' stroke-linecap='butt'/>\\n   <polygon points='783.43,30.22 786.07,25.66 780.80,25.66' fill='#333333' fill-opacity='1' stroke='#333333' stroke-opacity='1' stroke-width='0.71' stroke-linejoin='round' stroke-linecap='round'/>\\n   <text x='755.69' y='22' font-size='7.47pt' font-family='IBM Plex Sans' fill='#333333' fill-opacity='1'>Election Day<\\/text>\\n   <line x1='245.53' y1='269.47' x2='245.53' y2='36.7' stroke='#333333' stroke-opacity='1' stroke-width='0.85' stroke-linejoin='round' stroke-linecap='butt'/>\\n   <polygon points='245.53,39.74 248.16,35.18 242.89,35.18' fill='#333333' fill-opacity='1' stroke='#333333' stroke-opacity='1' stroke-width='0.71' stroke-linejoin='round' stroke-linecap='round'/>\\n   <text x='218.96' y='29.85' font-size='7.47pt' font-family='IBM Plex Sans' fill='#FFFFFF' fill-opacity='1'>August 22nd<\\/text>\\n   <text x='218.51' y='29.18' font-size='7.47pt' font-family='IBM Plex Sans' fill='#FFFFFF' fill-opacity='1'>August 22nd<\\/text>\\n   <text x='217.83' y='28.73' font-size='7.47pt' font-family='IBM Plex Sans' fill='#FFFFFF' fill-opacity='1'>August 22nd<\\/text>\\n   <text x='217.03' y='28.57' font-size='7.47pt' font-family='IBM Plex Sans' fill='#FFFFFF' fill-opacity='1'>August 22nd<\\/text>\\n   <text x='216.23' y='28.73' font-size='7.47pt' font-family='IBM Plex Sans' fill='#FFFFFF' fill-opacity='1'>August 22nd<\\/text>\\n   <text x='215.56' y='29.18' font-size='7.47pt' font-family='IBM Plex Sans' fill='#FFFFFF' fill-opacity='1'>August 22nd<\\/text>\\n   <text x='215.11' y='29.85' font-size='7.47pt' font-family='IBM Plex Sans' fill='#FFFFFF' fill-opacity='1'>August 22nd<\\/text>\\n   <text x='214.95' y='30.65' font-size='7.47pt' font-family='IBM Plex Sans' fill='#FFFFFF' fill-opacity='1'>August 22nd<\\/text>\\n   <text x='215.11' y='31.45' font-size='7.47pt' font-family='IBM Plex Sans' fill='#FFFFFF' fill-opacity='1'>August 22nd<\\/text>\\n   <text x='215.56' y='32.13' font-size='7.47pt' font-family='IBM Plex Sans' fill='#FFFFFF' fill-opacity='1'>August 22nd<\\/text>\\n   <text x='216.23' y='32.58' font-size='7.47pt' font-family='IBM Plex Sans' fill='#FFFFFF' fill-opacity='1'>August 22nd<\\/text>\\n   <text x='217.03' y='32.74' font-size='7.47pt' font-family='IBM Plex Sans' fill='#FFFFFF' fill-opacity='1'>August 22nd<\\/text>\\n   <text x='217.83' y='32.58' font-size='7.47pt' font-family='IBM Plex Sans' fill='#FFFFFF' fill-opacity='1'>August 22nd<\\/text>\\n   <text x='218.51' y='32.13' font-size='7.47pt' font-family='IBM Plex Sans' fill='#FFFFFF' fill-opacity='1'>August 22nd<\\/text>\\n   <text x='218.96' y='31.45' font-size='7.47pt' font-family='IBM Plex Sans' fill='#FFFFFF' fill-opacity='1'>August 22nd<\\/text>\\n   <text x='219.12' y='30.65' font-size='7.47pt' font-family='IBM Plex Sans' fill='#FFFFFF' fill-opacity='1'>August 22nd<\\/text>\\n   <text x='217.03' y='30.65' font-size='7.47pt' font-family='IBM Plex Sans' fill='#333333' fill-opacity='1'>August 22nd<\\/text>\\n   <line x1='5.98' y1='269.47' x2='858.02' y2='269.47' stroke='#363A3C' stroke-opacity='1' stroke-width='0.64' stroke-linejoin='round' stroke-linecap='butt'/>\\n   <polyline points='94.91,173.73 102.08,172.94 109.26,173.70 116.43,174.86 123.60,174.63 130.77,176.21 137.94,176.47 145.12,176.17 152.29,176.46 159.46,175.80 166.63,176.45 173.80,176.97 180.98,176.95 188.15,176.74 195.32,176.86 202.49,177.01 209.67,175.53 216.84,176.04 224.01,176.50 231.18,177.99 238.35,177.70 245.53,178.41' fill='none' stroke='#FFFFFF' stroke-opacity='1' stroke-width='5.33' stroke-linejoin='round' stroke-linecap='butt'/>\\n   <polyline points='94.91,173.73 102.08,172.94 109.26,173.70 116.43,174.86 123.60,174.63 130.77,176.21 137.94,176.47 145.12,176.17 152.29,176.46 159.46,175.80 166.63,176.45 173.80,176.97 180.98,176.95 188.15,176.74 195.32,176.86 202.49,177.01 209.67,175.53 216.84,176.04 224.01,176.50 231.18,177.99 238.35,177.70 245.53,178.41' fill='none' stroke='#B13737' stroke-opacity='1' stroke-width='1.71' stroke-linejoin='round' stroke-linecap='butt'/>\\n   <polyline points='94.91,132.44 102.08,133.23 109.26,132.48 116.43,131.32 123.60,131.54 130.77,129.96 137.94,129.70 145.12,130.00 152.29,129.72 159.46,130.37 166.63,129.72 173.80,129.21 180.98,129.22 188.15,129.44 195.32,129.31 202.49,129.16 209.67,130.64 216.84,130.13 224.01,129.67 231.18,128.19 238.35,128.47 245.53,127.77' fill='none' stroke='#FFFFFF' stroke-opacity='1' stroke-width='5.33' stroke-linejoin='round' stroke-linecap='butt'/>\\n   <polyline points='94.91,132.44 102.08,133.23 109.26,132.48 116.43,131.32 123.60,131.54 130.77,129.96 137.94,129.70 145.12,130.00 152.29,129.72 159.46,130.37 166.63,129.72 173.80,129.21 180.98,129.22 188.15,129.44 195.32,129.31 202.49,129.16 209.67,130.64 216.84,130.13 224.01,129.67 231.18,128.19 238.35,128.47 245.53,127.77' fill='none' stroke='#3579AC' stroke-opacity='1' stroke-width='1.71' stroke-linejoin='round' stroke-linecap='butt'/>\\n   <circle cx='245.53' cy='178.41' r='2.27pt' fill='#B13737' fill-opacity='1' stroke='#B13737' stroke-opacity='1' stroke-width='0.71' stroke-linejoin='round' stroke-linecap='round'/>\\n   <circle cx='245.53' cy='127.77' r='2.27pt' fill='#3579AC' fill-opacity='1' stroke='#3579AC' stroke-opacity='1' stroke-width='0.71' stroke-linejoin='round' stroke-linecap='round'/>\\n   <text x='261.28' y='172.37' font-size='10.67pt' font-weight='bold' font-family='IBM Plex Sans' fill='#FFFFFF' fill-opacity='1'>Trump<\\/text>\\n   <text x='261.29' y='192.85' font-size='10.67pt' font-weight='bold' font-family='IBM Plex Sans' fill='#FFFFFF' fill-opacity='1'>46.4%<\\/text>\\n   <text x='260.85' y='171.72' font-size='10.67pt' font-weight='bold' font-family='IBM Plex Sans' fill='#FFFFFF' fill-opacity='1'>Trump<\\/text>\\n   <text x='260.86' y='192.21' font-size='10.67pt' font-weight='bold' font-family='IBM Plex Sans' fill='#FFFFFF' fill-opacity='1'>46.4%<\\/text>\\n   <text x='260.2' y='171.29' font-size='10.67pt' font-weight='bold' font-family='IBM Plex Sans' fill='#FFFFFF' fill-opacity='1'>Trump<\\/text>\\n   <text x='260.22' y='191.78' font-size='10.67pt' font-weight='bold' font-family='IBM Plex Sans' fill='#FFFFFF' fill-opacity='1'>46.4%<\\/text>\\n   <text x='259.44' y='171.14' font-size='10.67pt' font-weight='bold' font-family='IBM Plex Sans' fill='#FFFFFF' fill-opacity='1'>Trump<\\/text>\\n   <text x='259.46' y='191.63' font-size='10.67pt' font-weight='bold' font-family='IBM Plex Sans' fill='#FFFFFF' fill-opacity='1'>46.4%<\\/text>\\n   <text x='258.68' y='171.29' font-size='10.67pt' font-weight='bold' font-family='IBM Plex Sans' fill='#FFFFFF' fill-opacity='1'>Trump<\\/text>\\n   <text x='258.7' y='191.78' font-size='10.67pt' font-weight='bold' font-family='IBM Plex Sans' fill='#FFFFFF' fill-opacity='1'>46.4%<\\/text>\\n   <text x='258.04' y='171.72' font-size='10.67pt' font-weight='bold' font-family='IBM Plex Sans' fill='#FFFFFF' fill-opacity='1'>Trump<\\/text>\\n   <text x='258.05' y='192.21' font-size='10.67pt' font-weight='bold' font-family='IBM Plex Sans' fill='#FFFFFF' fill-opacity='1'>46.4%<\\/text>\\n   <text x='257.61' y='172.37' font-size='10.67pt' font-weight='bold' font-family='IBM Plex Sans' fill='#FFFFFF' fill-opacity='1'>Trump<\\/text>\\n   <text x='257.62' y='192.85' font-size='10.67pt' font-weight='bold' font-family='IBM Plex Sans' fill='#FFFFFF' fill-opacity='1'>46.4%<\\/text>\\n   <text x='257.46' y='173.13' font-size='10.67pt' font-weight='bold' font-family='IBM Plex Sans' fill='#FFFFFF' fill-opacity='1'>Trump<\\/text>\\n   <text x='257.47' y='193.61' font-size='10.67pt' font-weight='bold' font-family='IBM Plex Sans' fill='#FFFFFF' fill-opacity='1'>46.4%<\\/text>\\n   <text x='257.61' y='173.89' font-size='10.67pt' font-weight='bold' font-family='IBM Plex Sans' fill='#FFFFFF' fill-opacity='1'>Trump<\\/text>\\n   <text x='257.62' y='194.37' font-size='10.67pt' font-weight='bold' font-family='IBM Plex Sans' fill='#FFFFFF' fill-opacity='1'>46.4%<\\/text>\\n   <text x='258.04' y='174.53' font-size='10.67pt' font-weight='bold' font-family='IBM Plex Sans' fill='#FFFFFF' fill-opacity='1'>Trump<\\/text>\\n   <text x='258.05' y='195.02' font-size='10.67pt' font-weight='bold' font-family='IBM Plex Sans' fill='#FFFFFF' fill-opacity='1'>46.4%<\\/text>\\n   <text x='258.68' y='174.96' font-size='10.67pt' font-weight='bold' font-family='IBM Plex Sans' fill='#FFFFFF' fill-opacity='1'>Trump<\\/text>\\n   <text x='258.7' y='195.45' font-size='10.67pt' font-weight='bold' font-family='IBM Plex Sans' fill='#FFFFFF' fill-opacity='1'>46.4%<\\/text>\\n   <text x='259.44' y='175.11' font-size='10.67pt' font-weight='bold' font-family='IBM Plex Sans' fill='#FFFFFF' fill-opacity='1'>Trump<\\/text>\\n   <text x='259.46' y='195.6' font-size='10.67pt' font-weight='bold' font-family='IBM Plex Sans' fill='#FFFFFF' fill-opacity='1'>46.4%<\\/text>\\n   <text x='260.2' y='174.96' font-size='10.67pt' font-weight='bold' font-family='IBM Plex Sans' fill='#FFFFFF' fill-opacity='1'>Trump<\\/text>\\n   <text x='260.22' y='195.45' font-size='10.67pt' font-weight='bold' font-family='IBM Plex Sans' fill='#FFFFFF' fill-opacity='1'>46.4%<\\/text>\\n   <text x='260.85' y='174.53' font-size='10.67pt' font-weight='bold' font-family='IBM Plex Sans' fill='#FFFFFF' fill-opacity='1'>Trump<\\/text>\\n   <text x='260.86' y='195.02' font-size='10.67pt' font-weight='bold' font-family='IBM Plex Sans' fill='#FFFFFF' fill-opacity='1'>46.4%<\\/text>\\n   <text x='261.28' y='173.89' font-size='10.67pt' font-weight='bold' font-family='IBM Plex Sans' fill='#FFFFFF' fill-opacity='1'>Trump<\\/text>\\n   <text x='261.29' y='194.37' font-size='10.67pt' font-weight='bold' font-family='IBM Plex Sans' fill='#FFFFFF' fill-opacity='1'>46.4%<\\/text>\\n   <text x='261.43' y='173.13' font-size='10.67pt' font-weight='bold' font-family='IBM Plex Sans' fill='#FFFFFF' fill-opacity='1'>Trump<\\/text>\\n   <text x='261.44' y='193.61' font-size='10.67pt' font-weight='bold' font-family='IBM Plex Sans' fill='#FFFFFF' fill-opacity='1'>46.4%<\\/text>\\n   <text x='259.44' y='173.13' font-size='10.67pt' font-weight='bold' font-family='IBM Plex Sans' fill='#B13737' fill-opacity='1'>Trump<\\/text>\\n   <text x='259.46' y='193.61' font-size='10.67pt' font-weight='bold' font-family='IBM Plex Sans' fill='#B13737' fill-opacity='1'>46.4%<\\/text>\\n   <text x='262.66' y='121.73' font-size='10.67pt' font-weight='bold' font-family='IBM Plex Sans' fill='#FFFFFF' fill-opacity='1'>Harris<\\/text>\\n   <text x='261.29' y='142.21' font-size='10.67pt' font-weight='bold' font-family='IBM Plex Sans' fill='#FFFFFF' fill-opacity='1'>53.6%<\\/text>\\n   <text x='262.23' y='121.08' font-size='10.67pt' font-weight='bold' font-family='IBM Plex Sans' fill='#FFFFFF' fill-opacity='1'>Harris<\\/text>\\n   <text x='260.86' y='141.57' font-size='10.67pt' font-weight='bold' font-family='IBM Plex Sans' fill='#FFFFFF' fill-opacity='1'>53.6%<\\/text>\\n   <text x='261.59' y='120.65' font-size='10.67pt' font-weight='bold' font-family='IBM Plex Sans' fill='#FFFFFF' fill-opacity='1'>Harris<\\/text>\\n   <text x='260.22' y='141.14' font-size='10.67pt' font-weight='bold' font-family='IBM Plex Sans' fill='#FFFFFF' fill-opacity='1'>53.6%<\\/text>\\n   <text x='260.83' y='120.5' font-size='10.67pt' font-weight='bold' font-family='IBM Plex Sans' fill='#FFFFFF' fill-opacity='1'>Harris<\\/text>\\n   <text x='259.46' y='140.99' font-size='10.67pt' font-weight='bold' font-family='IBM Plex Sans' fill='#FFFFFF' fill-opacity='1'>53.6%<\\/text>\\n   <text x='260.07' y='120.65' font-size='10.67pt' font-weight='bold' font-family='IBM Plex Sans' fill='#FFFFFF' fill-opacity='1'>Harris<\\/text>\\n   <text x='258.7' y='141.14' font-size='10.67pt' font-weight='bold' font-family='IBM Plex Sans' fill='#FFFFFF' fill-opacity='1'>53.6%<\\/text>\\n   <text x='259.43' y='121.08' font-size='10.67pt' font-weight='bold' font-family='IBM Plex Sans' fill='#FFFFFF' fill-opacity='1'>Harris<\\/text>\\n   <text x='258.05' y='141.57' font-size='10.67pt' font-weight='bold' font-family='IBM Plex Sans' fill='#FFFFFF' fill-opacity='1'>53.6%<\\/text>\\n   <text x='259' y='121.73' font-size='10.67pt' font-weight='bold' font-family='IBM Plex Sans' fill='#FFFFFF' fill-opacity='1'>Harris<\\/text>\\n   <text x='257.62' y='142.21' font-size='10.67pt' font-weight='bold' font-family='IBM Plex Sans' fill='#FFFFFF' fill-opacity='1'>53.6%<\\/text>\\n   <text x='258.84' y='122.49' font-size='10.67pt' font-weight='bold' font-family='IBM Plex Sans' fill='#FFFFFF' fill-opacity='1'>Harris<\\/text>\\n   <text x='257.47' y='142.97' font-size='10.67pt' font-weight='bold' font-family='IBM Plex Sans' fill='#FFFFFF' fill-opacity='1'>53.6%<\\/text>\\n   <text x='259' y='123.25' font-size='10.67pt' font-weight='bold' font-family='IBM Plex Sans' fill='#FFFFFF' fill-opacity='1'>Harris<\\/text>\\n   <text x='257.62' y='143.73' font-size='10.67pt' font-weight='bold' font-family='IBM Plex Sans' fill='#FFFFFF' fill-opacity='1'>53.6%<\\/text>\\n   <text x='259.43' y='123.89' font-size='10.67pt' font-weight='bold' font-family='IBM Plex Sans' fill='#FFFFFF' fill-opacity='1'>Harris<\\/text>\\n   <text x='258.05' y='144.38' font-size='10.67pt' font-weight='bold' font-family='IBM Plex Sans' fill='#FFFFFF' fill-opacity='1'>53.6%<\\/text>\\n   <text x='260.07' y='124.32' font-size='10.67pt' font-weight='bold' font-family='IBM Plex Sans' fill='#FFFFFF' fill-opacity='1'>Harris<\\/text>\\n   <text x='258.7' y='144.81' font-size='10.67pt' font-weight='bold' font-family='IBM Plex Sans' fill='#FFFFFF' fill-opacity='1'>53.6%<\\/text>\\n   <text x='260.83' y='124.47' font-size='10.67pt' font-weight='bold' font-family='IBM Plex Sans' fill='#FFFFFF' fill-opacity='1'>Harris<\\/text>\\n   <text x='259.46' y='144.96' font-size='10.67pt' font-weight='bold' font-family='IBM Plex Sans' fill='#FFFFFF' fill-opacity='1'>53.6%<\\/text>\\n   <text x='261.59' y='124.32' font-size='10.67pt' font-weight='bold' font-family='IBM Plex Sans' fill='#FFFFFF' fill-opacity='1'>Harris<\\/text>\\n   <text x='260.22' y='144.81' font-size='10.67pt' font-weight='bold' font-family='IBM Plex Sans' fill='#FFFFFF' fill-opacity='1'>53.6%<\\/text>\\n   <text x='262.23' y='123.89' font-size='10.67pt' font-weight='bold' font-family='IBM Plex Sans' fill='#FFFFFF' fill-opacity='1'>Harris<\\/text>\\n   <text x='260.86' y='144.38' font-size='10.67pt' font-weight='bold' font-family='IBM Plex Sans' fill='#FFFFFF' fill-opacity='1'>53.6%<\\/text>\\n   <text x='262.66' y='123.25' font-size='10.67pt' font-weight='bold' font-family='IBM Plex Sans' fill='#FFFFFF' fill-opacity='1'>Harris<\\/text>\\n   <text x='261.29' y='143.73' font-size='10.67pt' font-weight='bold' font-family='IBM Plex Sans' fill='#FFFFFF' fill-opacity='1'>53.6%<\\/text>\\n   <text x='262.82' y='122.49' font-size='10.67pt' font-weight='bold' font-family='IBM Plex Sans' fill='#FFFFFF' fill-opacity='1'>Harris<\\/text>\\n   <text x='261.44' y='142.97' font-size='10.67pt' font-weight='bold' font-family='IBM Plex Sans' fill='#FFFFFF' fill-opacity='1'>53.6%<\\/text>\\n   <text x='260.83' y='122.49' font-size='10.67pt' font-weight='bold' font-family='IBM Plex Sans' fill='#3579AC' fill-opacity='1'>Harris<\\/text>\\n   <text x='259.46' y='142.97' font-size='10.67pt' font-weight='bold' font-family='IBM Plex Sans' fill='#3579AC' fill-opacity='1'>53.6%<\\/text>\\n   <rect id='svg_9ecb741d_d9b0_4769_8c13_9345064f3834_e1' x='91.33' y='36.7' width='7.17' height='232.78' fill='#333333' fill-opacity='0' stroke='none' title='August 1st&amp;lt;br&amp;gt;Harris: &amp;lt;span style=&amp;#39;float:right;&amp;#39;&amp;gt;52.9%&amp;lt;/span&amp;gt;&amp;lt;br&amp;gt;Trump: &amp;lt;span style=&amp;#39;float:right;&amp;#39;&amp;gt;47.1%&amp;lt;/span&amp;gt;'/>\\n   <rect id='svg_9ecb741d_d9b0_4769_8c13_9345064f3834_e2' x='98.5' y='36.7' width='7.17' height='232.78' fill='#333333' fill-opacity='0' stroke='none' title='August 2nd&amp;lt;br&amp;gt;Harris: &amp;lt;span style=&amp;#39;float:right;&amp;#39;&amp;gt;52.8%&amp;lt;/span&amp;gt;&amp;lt;br&amp;gt;Trump: &amp;lt;span style=&amp;#39;float:right;&amp;#39;&amp;gt;47.2%&amp;lt;/span&amp;gt;'/>\\n   <rect id='svg_9ecb741d_d9b0_4769_8c13_9345064f3834_e3' x='105.67' y='36.7' width='7.17' height='232.78' fill='#333333' fill-opacity='0' stroke='none' title='August 3rd&amp;lt;br&amp;gt;Harris: &amp;lt;span style=&amp;#39;float:right;&amp;#39;&amp;gt;52.9%&amp;lt;/span&amp;gt;&amp;lt;br&amp;gt;Trump: &amp;lt;span style=&amp;#39;float:right;&amp;#39;&amp;gt;47.1%&amp;lt;/span&amp;gt;'/>\\n   <rect id='svg_9ecb741d_d9b0_4769_8c13_9345064f3834_e4' x='112.84' y='36.7' width='7.17' height='232.78' fill='#333333' fill-opacity='0' stroke='none' title='August 4th&amp;lt;br&amp;gt;Harris: &amp;lt;span style=&amp;#39;float:right;&amp;#39;&amp;gt;53.1%&amp;lt;/span&amp;gt;&amp;lt;br&amp;gt;Trump: &amp;lt;span style=&amp;#39;float:right;&amp;#39;&amp;gt;46.9%&amp;lt;/span&amp;gt;'/>\\n   <rect id='svg_9ecb741d_d9b0_4769_8c13_9345064f3834_e5' x='120.01' y='36.7' width='7.17' height='232.78' fill='#333333' fill-opacity='0' stroke='none' title='August 5th&amp;lt;br&amp;gt;Harris: &amp;lt;span style=&amp;#39;float:right;&amp;#39;&amp;gt;53.1%&amp;lt;/span&amp;gt;&amp;lt;br&amp;gt;Trump: &amp;lt;span style=&amp;#39;float:right;&amp;#39;&amp;gt;46.9%&amp;lt;/span&amp;gt;'/>\\n   <rect id='svg_9ecb741d_d9b0_4769_8c13_9345064f3834_e6' x='127.19' y='36.7' width='7.17' height='232.78' fill='#333333' fill-opacity='0' stroke='none' title='August 6th&amp;lt;br&amp;gt;Harris: &amp;lt;span style=&amp;#39;float:right;&amp;#39;&amp;gt;53.3%&amp;lt;/span&amp;gt;&amp;lt;br&amp;gt;Trump: &amp;lt;span style=&amp;#39;float:right;&amp;#39;&amp;gt;46.7%&amp;lt;/span&amp;gt;'/>\\n   <rect id='svg_9ecb741d_d9b0_4769_8c13_9345064f3834_e7' x='134.36' y='36.7' width='7.17' height='232.78' fill='#333333' fill-opacity='0' stroke='none' title='August 7th&amp;lt;br&amp;gt;Harris: &amp;lt;span style=&amp;#39;float:right;&amp;#39;&amp;gt;53.3%&amp;lt;/span&amp;gt;&amp;lt;br&amp;gt;Trump: &amp;lt;span style=&amp;#39;float:right;&amp;#39;&amp;gt;46.7%&amp;lt;/span&amp;gt;'/>\\n   <rect id='svg_9ecb741d_d9b0_4769_8c13_9345064f3834_e8' x='141.53' y='36.7' width='7.17' height='232.78' fill='#333333' fill-opacity='0' stroke='none' title='August 8th&amp;lt;br&amp;gt;Harris: &amp;lt;span style=&amp;#39;float:right;&amp;#39;&amp;gt;53.3%&amp;lt;/span&amp;gt;&amp;lt;br&amp;gt;Trump: &amp;lt;span style=&amp;#39;float:right;&amp;#39;&amp;gt;46.7%&amp;lt;/span&amp;gt;'/>\\n   <rect id='svg_9ecb741d_d9b0_4769_8c13_9345064f3834_e9' x='148.7' y='36.7' width='7.17' height='232.78' fill='#333333' fill-opacity='0' stroke='none' title='August 9th&amp;lt;br&amp;gt;Harris: &amp;lt;span style=&amp;#39;float:right;&amp;#39;&amp;gt;53.3%&amp;lt;/span&amp;gt;&amp;lt;br&amp;gt;Trump: &amp;lt;span style=&amp;#39;float:right;&amp;#39;&amp;gt;46.7%&amp;lt;/span&amp;gt;'/>\\n   <rect id='svg_9ecb741d_d9b0_4769_8c13_9345064f3834_e10' x='155.87' y='36.7' width='7.17' height='232.78' fill='#333333' fill-opacity='0' stroke='none' title='August 10th&amp;lt;br&amp;gt;Harris: &amp;lt;span style=&amp;#39;float:right;&amp;#39;&amp;gt;53.2%&amp;lt;/span&amp;gt;&amp;lt;br&amp;gt;Trump: &amp;lt;span style=&amp;#39;float:right;&amp;#39;&amp;gt;46.8%&amp;lt;/span&amp;gt;'/>\\n   <rect id='svg_9ecb741d_d9b0_4769_8c13_9345064f3834_e11' x='163.05' y='36.7' width='7.17' height='232.78' fill='#333333' fill-opacity='0' stroke='none' title='August 11th&amp;lt;br&amp;gt;Harris: &amp;lt;span style=&amp;#39;float:right;&amp;#39;&amp;gt;53.3%&amp;lt;/span&amp;gt;&amp;lt;br&amp;gt;Trump: &amp;lt;span style=&amp;#39;float:right;&amp;#39;&amp;gt;46.7%&amp;lt;/span&amp;gt;'/>\\n   <rect id='svg_9ecb741d_d9b0_4769_8c13_9345064f3834_e12' x='170.22' y='36.7' width='7.17' height='232.78' fill='#333333' fill-opacity='0' stroke='none' title='August 12th&amp;lt;br&amp;gt;Harris: &amp;lt;span style=&amp;#39;float:right;&amp;#39;&amp;gt;53.4%&amp;lt;/span&amp;gt;&amp;lt;br&amp;gt;Trump: &amp;lt;span style=&amp;#39;float:right;&amp;#39;&amp;gt;46.6%&amp;lt;/span&amp;gt;'/>\\n   <rect id='svg_9ecb741d_d9b0_4769_8c13_9345064f3834_e13' x='177.39' y='36.7' width='7.17' height='232.78' fill='#333333' fill-opacity='0' stroke='none' title='August 13th&amp;lt;br&amp;gt;Harris: &amp;lt;span style=&amp;#39;float:right;&amp;#39;&amp;gt;53.4%&amp;lt;/span&amp;gt;&amp;lt;br&amp;gt;Trump: &amp;lt;span style=&amp;#39;float:right;&amp;#39;&amp;gt;46.6%&amp;lt;/span&amp;gt;'/>\\n   <rect id='svg_9ecb741d_d9b0_4769_8c13_9345064f3834_e14' x='184.56' y='36.7' width='7.17' height='232.78' fill='#333333' fill-opacity='0' stroke='none' title='August 14th&amp;lt;br&amp;gt;Harris: &amp;lt;span style=&amp;#39;float:right;&amp;#39;&amp;gt;53.4%&amp;lt;/span&amp;gt;&amp;lt;br&amp;gt;Trump: &amp;lt;span style=&amp;#39;float:right;&amp;#39;&amp;gt;46.6%&amp;lt;/span&amp;gt;'/>\\n   <rect id='svg_9ecb741d_d9b0_4769_8c13_9345064f3834_e15' x='191.73' y='36.7' width='7.17' height='232.78' fill='#333333' fill-opacity='0' stroke='none' title='August 15th&amp;lt;br&amp;gt;Harris: &amp;lt;span style=&amp;#39;float:right;&amp;#39;&amp;gt;53.4%&amp;lt;/span&amp;gt;&amp;lt;br&amp;gt;Trump: &amp;lt;span style=&amp;#39;float:right;&amp;#39;&amp;gt;46.6%&amp;lt;/span&amp;gt;'/>\\n   <rect id='svg_9ecb741d_d9b0_4769_8c13_9345064f3834_e16' x='198.91' y='36.7' width='7.17' height='232.78' fill='#333333' fill-opacity='0' stroke='none' title='August 16th&amp;lt;br&amp;gt;Harris: &amp;lt;span style=&amp;#39;float:right;&amp;#39;&amp;gt;53.4%&amp;lt;/span&amp;gt;&amp;lt;br&amp;gt;Trump: &amp;lt;span style=&amp;#39;float:right;&amp;#39;&amp;gt;46.6%&amp;lt;/span&amp;gt;'/>\\n   <rect id='svg_9ecb741d_d9b0_4769_8c13_9345064f3834_e17' x='206.08' y='36.7' width='7.17' height='232.78' fill='#333333' fill-opacity='0' stroke='none' title='August 17th&amp;lt;br&amp;gt;Harris: &amp;lt;span style=&amp;#39;float:right;&amp;#39;&amp;gt;53.2%&amp;lt;/span&amp;gt;&amp;lt;br&amp;gt;Trump: &amp;lt;span style=&amp;#39;float:right;&amp;#39;&amp;gt;46.8%&amp;lt;/span&amp;gt;'/>\\n   <rect id='svg_9ecb741d_d9b0_4769_8c13_9345064f3834_e18' x='213.25' y='36.7' width='7.17' height='232.78' fill='#333333' fill-opacity='0' stroke='none' title='August 18th&amp;lt;br&amp;gt;Harris: &amp;lt;span style=&amp;#39;float:right;&amp;#39;&amp;gt;53.3%&amp;lt;/span&amp;gt;&amp;lt;br&amp;gt;Trump: &amp;lt;span style=&amp;#39;float:right;&amp;#39;&amp;gt;46.7%&amp;lt;/span&amp;gt;'/>\\n   <rect id='svg_9ecb741d_d9b0_4769_8c13_9345064f3834_e19' x='220.42' y='36.7' width='7.17' height='232.78' fill='#333333' fill-opacity='0' stroke='none' title='August 19th&amp;lt;br&amp;gt;Harris: &amp;lt;span style=&amp;#39;float:right;&amp;#39;&amp;gt;53.3%&amp;lt;/span&amp;gt;&amp;lt;br&amp;gt;Trump: &amp;lt;span style=&amp;#39;float:right;&amp;#39;&amp;gt;46.7%&amp;lt;/span&amp;gt;'/>\\n   <rect id='svg_9ecb741d_d9b0_4769_8c13_9345064f3834_e20' x='227.6' y='36.7' width='7.17' height='232.78' fill='#333333' fill-opacity='0' stroke='none' title='August 20th&amp;lt;br&amp;gt;Harris: &amp;lt;span style=&amp;#39;float:right;&amp;#39;&amp;gt;53.5%&amp;lt;/span&amp;gt;&amp;lt;br&amp;gt;Trump: &amp;lt;span style=&amp;#39;float:right;&amp;#39;&amp;gt;46.5%&amp;lt;/span&amp;gt;'/>\\n   <rect id='svg_9ecb741d_d9b0_4769_8c13_9345064f3834_e21' x='234.77' y='36.7' width='7.17' height='232.78' fill='#333333' fill-opacity='0' stroke='none' title='August 21st&amp;lt;br&amp;gt;Harris: &amp;lt;span style=&amp;#39;float:right;&amp;#39;&amp;gt;53.5%&amp;lt;/span&amp;gt;&amp;lt;br&amp;gt;Trump: &amp;lt;span style=&amp;#39;float:right;&amp;#39;&amp;gt;46.5%&amp;lt;/span&amp;gt;'/>\\n   <rect id='svg_9ecb741d_d9b0_4769_8c13_9345064f3834_e22' x='241.94' y='36.7' width='7.17' height='232.78' fill='#333333' fill-opacity='0' stroke='none' title='August 22nd&amp;lt;br&amp;gt;Harris: &amp;lt;span style=&amp;#39;float:right;&amp;#39;&amp;gt;53.6%&amp;lt;/span&amp;gt;&amp;lt;br&amp;gt;Trump: &amp;lt;span style=&amp;#39;float:right;&amp;#39;&amp;gt;46.4%&amp;lt;/span&amp;gt;'/>\\n  <\\/g>\\n <\\/g>\\n<\\/svg>\",\"js\":null,\"uid\":\"svg_9ecb741d_d9b0_4769_8c13_9345064f3834\",\"ratio\":3,\"settings\":{\"tooltip\":{\"css\":\".tooltip_SVGID_ { font-family:IBM Plex Sans;color:#363a3c;background-color:#fafafa;padding:5px;border-radius:3px;border-color:black;border-style:solid;border-width:0.125em 0em 0em 0em;box-shadow: 0px 0px 10px 5px lightgray;min-width: 120px ; position:absolute;pointer-events:none;z-index:999;}\",\"placement\":\"doc\",\"opacity\":1,\"offx\":10,\"offy\":0,\"use_cursor_pos\":true,\"use_fill\":false,\"use_stroke\":false,\"delay_over\":200,\"delay_out\":500},\"hover\":{\"css\":\".hover_data_SVGID_ { fill:orange;stroke:black;cursor:pointer; }\\ntext.hover_data_SVGID_ { stroke:none;fill:orange; }\\ncircle.hover_data_SVGID_ { fill:orange;stroke:black; }\\nline.hover_data_SVGID_, polyline.hover_data_SVGID_ { fill:none;stroke:orange; }\\nrect.hover_data_SVGID_, polygon.hover_data_SVGID_, path.hover_data_SVGID_ { fill:orange;stroke:none; }\\nimage.hover_data_SVGID_ { stroke:orange; }\",\"reactive\":true,\"nearest_distance\":null},\"hover_inv\":{\"css\":\"\"},\"hover_key\":{\"css\":\".hover_key_SVGID_ { fill:orange;stroke:black;cursor:pointer; }\\ntext.hover_key_SVGID_ { stroke:none;fill:orange; }\\ncircle.hover_key_SVGID_ { fill:orange;stroke:black; }\\nline.hover_key_SVGID_, polyline.hover_key_SVGID_ { fill:none;stroke:orange; }\\nrect.hover_key_SVGID_, polygon.hover_key_SVGID_, path.hover_key_SVGID_ { fill:orange;stroke:none; }\\nimage.hover_key_SVGID_ { stroke:orange; }\",\"reactive\":true},\"hover_theme\":{\"css\":\".hover_theme_SVGID_ { fill:orange;stroke:black;cursor:pointer; }\\ntext.hover_theme_SVGID_ { stroke:none;fill:orange; }\\ncircle.hover_theme_SVGID_ { fill:orange;stroke:black; }\\nline.hover_theme_SVGID_, polyline.hover_theme_SVGID_ { fill:none;stroke:orange; }\\nrect.hover_theme_SVGID_, polygon.hover_theme_SVGID_, path.hover_theme_SVGID_ { fill:orange;stroke:none; }\\nimage.hover_theme_SVGID_ { stroke:orange; }\",\"reactive\":true},\"select\":{\"css\":\".select_data_SVGID_ { fill:red;stroke:black;cursor:pointer; }\\ntext.select_data_SVGID_ { stroke:none;fill:red; }\\ncircle.select_data_SVGID_ { fill:red;stroke:black; }\\nline.select_data_SVGID_, polyline.select_data_SVGID_ { fill:none;stroke:red; }\\nrect.select_data_SVGID_, polygon.select_data_SVGID_, path.select_data_SVGID_ { fill:red;stroke:none; }\\nimage.select_data_SVGID_ { stroke:red; }\",\"type\":\"multiple\",\"only_shiny\":true,\"selected\":[]},\"select_inv\":{\"css\":\"\"},\"select_key\":{\"css\":\".select_key_SVGID_ { fill:red;stroke:black;cursor:pointer; }\\ntext.select_key_SVGID_ { stroke:none;fill:red; }\\ncircle.select_key_SVGID_ { fill:red;stroke:black; }\\nline.select_key_SVGID_, polyline.select_key_SVGID_ { fill:none;stroke:red; }\\nrect.select_key_SVGID_, polygon.select_key_SVGID_, path.select_key_SVGID_ { fill:red;stroke:none; }\\nimage.select_key_SVGID_ { stroke:red; }\",\"type\":\"single\",\"only_shiny\":true,\"selected\":[]},\"select_theme\":{\"css\":\".select_theme_SVGID_ { fill:red;stroke:black;cursor:pointer; }\\ntext.select_theme_SVGID_ { stroke:none;fill:red; }\\ncircle.select_theme_SVGID_ { fill:red;stroke:black; }\\nline.select_theme_SVGID_, polyline.select_theme_SVGID_ { fill:none;stroke:red; }\\nrect.select_theme_SVGID_, polygon.select_theme_SVGID_, path.select_theme_SVGID_ { fill:red;stroke:none; }\\nimage.select_theme_SVGID_ { stroke:red; }\",\"type\":\"single\",\"only_shiny\":true,\"selected\":[]},\"zoom\":{\"min\":1,\"max\":1,\"duration\":300},\"toolbar\":{\"position\":\"topright\",\"pngname\":\"diagram\",\"tooltips\":null,\"fixed\":false,\"hidden\":[],\"delay_over\":200,\"delay_out\":500},\"sizing\":{\"rescale\":true,\"width\":1}}},\"evals\":[],\"jsHooks\":[]}</script>\n```\n\n:::\n:::\n\n<br><span style='display:inline-block;width:60%;'>*No polls have been conducted in Colorado. The projected voteshare is estimated using economic and approval indicators, as well as polling information from similar states.*</span><br>\n\n::: {.cell}\n\n:::\n\n\n\n---\n\n:::: {.columns}\n::: {.column width=\"60%\"}\n\n\n### <span style='font-family:Playfair Display;'>State similarities</span>\nThe model uses state characteristics, like demographic composition, population density, and education, to estimate how similar states are to one another.\nSimilar states are more likely to share polling biases and see similar shifts in polling trendlines.\n\n\n:::\n::: {.column width=\"40%\"}\n:::\n::::\n\n\n\n![](https://raw.githubusercontent.com/markjrieke/2024-potus/main/img/Colorado.png){height=700 fig-align='center'}\n\n\n\n---\n\n:::: {.columns}\n::: {.column width=\"30%\"}\n\n\n<span style='color:gray;font-size:12px'>\nSources: Ballotpedia; Cook Political Report; The Economist; Federal Reserve Bank of St. Louis; FiveThirtyEight; Urban Stats; 270towin.com\n<br>\n<br>\n[{{< fa brands github >}} View the source code](https://github.com/markjrieke/2024-potus/tree/main)\n<br>\n[{{< fa solid database >}} Explore the output](https://github.com/markjrieke/2024-potus/tree/main/out)\n</span>\n\n\n:::\n::::\n\n---\n\n:::::\n\n::::: {.column-margin-custom}\n\n\n\n**[National Forecast](National.qmd)**<br>[How this works](../posts/2024-07-04-forecast-methodology/index.qmd)\n\n<br>**Competitive states**<br>[Wisconsin](Wisconsin.qmd)<br>[Michigan](Michigan.qmd)<br>[Pennsylvania](Pennsylvania.qmd)<br>[Nevada](Nevada.qmd)<br>[Arizona](Arizona.qmd)<br>[Maine CD-2](Maine CD-2.qmd)<br>[Georgia](Georgia.qmd)<br>[North Carolina](North Carolina.qmd)<br>[Nebraska CD-2](Nebraska CD-2.qmd)<br>[New Hampshire](New Hampshire.qmd)<br>[Virginia](Virginia.qmd)<br>[Minnesota](Minnesota.qmd)<br>[New Mexico](New Mexico.qmd)<br>[Colorado](Colorado.qmd)<br>[Florida](Florida.qmd)\n\n<br>**All states**<br>[Alabama](Alabama.qmd)<br>[Alaska](Alaska.qmd)<br>[Arizona](Arizona.qmd)<br>[Arkansas](Arkansas.qmd)<br>[California](California.qmd)<br>[Colorado](Colorado.qmd)<br>[Connecticut](Connecticut.qmd)<br>[Delaware](Delaware.qmd)<br>[District of Columbia](District of Columbia.qmd)<br>[Florida](Florida.qmd)<br>[Georgia](Georgia.qmd)<br>[Hawaii](Hawaii.qmd)<br>[Idaho](Idaho.qmd)<br>[Illinois](Illinois.qmd)<br>[Indiana](Indiana.qmd)<br>[Iowa](Iowa.qmd)<br>[Kansas](Kansas.qmd)<br>[Kentucky](Kentucky.qmd)<br>[Louisiana](Louisiana.qmd)<br>[Maine CD-1](Maine CD-1.qmd)<br>[Maine CD-2](Maine CD-2.qmd)<br>[Maine](Maine.qmd)<br>[Maryland](Maryland.qmd)<br>[Massachusetts](Massachusetts.qmd)<br>[Michigan](Michigan.qmd)<br>[Minnesota](Minnesota.qmd)<br>[Mississippi](Mississippi.qmd)<br>[Missouri](Missouri.qmd)<br>[Montana](Montana.qmd)<br>[Nebraska CD-1](Nebraska CD-1.qmd)<br>[Nebraska CD-2](Nebraska CD-2.qmd)<br>[Nebraska CD-3](Nebraska CD-3.qmd)<br>[Nebraska](Nebraska.qmd)<br>[Nevada](Nevada.qmd)<br>[New Hampshire](New Hampshire.qmd)<br>[New Jersey](New Jersey.qmd)<br>[New Mexico](New Mexico.qmd)<br>[New York](New York.qmd)<br>[North Carolina](North Carolina.qmd)<br>[North Dakota](North Dakota.qmd)<br>[Ohio](Ohio.qmd)<br>[Oklahoma](Oklahoma.qmd)<br>[Oregon](Oregon.qmd)<br>[Pennsylvania](Pennsylvania.qmd)<br>[Rhode Island](Rhode Island.qmd)<br>[South Carolina](South Carolina.qmd)<br>[South Dakota](South Dakota.qmd)<br>[Tennessee](Tennessee.qmd)<br>[Texas](Texas.qmd)<br>[Utah](Utah.qmd)<br>[Vermont](Vermont.qmd)<br>[Virginia](Virginia.qmd)<br>[Washington](Washington.qmd)<br>[West Virginia](West Virginia.qmd)<br>[Wisconsin](Wisconsin.qmd)<br>[Wyoming](Wyoming.qmd)\n\n\n\n:::::\n\n",
    "supporting": [],
    "filters": [
      "rmarkdown/pagebreak.lua"
    ],
    "includes": {
      "include-in-header": [
        "<link href=\"../site_libs/htmltools-fill-0.5.8.1/fill.css\" rel=\"stylesheet\" />\n<script src=\"../site_libs/htmlwidgets-1.6.4/htmlwidgets.js\"></script>\n<script src=\"../site_libs/d3-bundle-5.16.0/d3-bundle.min.js\"></script>\n<script src=\"../site_libs/d3-lasso-0.0.5/d3-lasso.min.js\"></script>\n<script src=\"../site_libs/save-svg-as-png-1.4.17/save-svg-as-png.min.js\"></script>\n<script src=\"../site_libs/flatbush-4.4.0/flatbush.min.js\"></script>\n<link href=\"../site_libs/ggiraphjs-0.8.10/ggiraphjs.min.css\" rel=\"stylesheet\" />\n<script src=\"../site_libs/ggiraphjs-0.8.10/ggiraphjs.min.js\"></script>\n<script src=\"../site_libs/girafe-binding-0.8.10/girafe.js\"></script>\n"
      ]
    },
    "engineDependencies": {},
    "preserve": {},
    "postProcess": true
  }
}